{"opass":"j3vsRXKz","c":"uJZ6NrvQ","org":"no","chp":181,"ochp":0,"ohp":90,"ivs":{"hp":11,"attack":19,"defense":20,"special_attack":20,"special_defense":19,"speed":21},"evs":{"hp":0,"attack":0,"defense":0,"special_attack":0,"special_defense":0,"speed":0},"nat":"Jolly","cpass":"lbxhu5u8","level":38,"name":"litwick","oability":"flame-body","omoves":[{"id":123,"learn_method":"level-up","level_learned_at":1},{"id":247,"learn_method":"level-up","level_learned_at":36},{"id":310,"learn_method":"level-up","level_learned_at":1},{"id":506,"learn_method":"level-up","level_learned_at":16}],"ded":[],"ot":{"litwick":0},"symbol":"","team":{"uJZ6NrvQ":181},"la":{"uJZ6NrvQ":62},"abilityState":{"entryOnce":{},"battleBond":{}},"statStages":{"uJZ6NrvQ":{"attack":0,"defense":0,"special_attack":0,"special_defense":0,"speed":0,"accuracy":0,"evasion":0},"j3vsRXKz":{"attack":0,"defense":0,"special_attack":0,"special_defense":0,"speed":0,"accuracy":0,"evasion":0}}}