{"impersonateState":{},"formState":{"originalName":{},"originalAbility":{}},"heldItems":{"SKYqEOrz":"none","Zk0uUgKy":"none","XO6qeZ2o":"none","4PI42M2M":"none","Qt8oEhjI":"none","DfxTckLr":"none","sgQPXGy6":"none"},"consumedHeldItems":{},"opass":"sgQPXGy6","c":"SKYqEOrz","org":"no","chp":109,"ochp":214,"ohp":214,"ivs":{"hp":30,"attack":27,"defense":29,"special_attack":26,"special_defense":25,"speed":26},"evs":{"hp":0,"attack":0,"defense":0,"special_attack":0,"special_defense":0,"speed":0},"nat":"Naive","cpass":"HxVEcKxe","level":62,"name":"zekrom","oheld_item":"none","oability":"teravolt","omoves":[{"id":337,"learn_method":"level-up","level_learned_at":32},{"id":422,"learn_method":"level-up","level_learned_at":1},{"id":428,"learn_method":"level-up","level_learned_at":24},{"id":559,"learn_method":"level-up","level_learned_at":48}],"ded":[],"ot":{"zekrom":214},"symbol":"","team":{"SKYqEOrz":109,"Zk0uUgKy":414,"XO6qeZ2o":377,"4PI42M2M":454,"Qt8oEhjI":319,"DfxTckLr":349},"la":{"SKYqEOrz":39,"Zk0uUgKy":100,"XO6qeZ2o":100,"4PI42M2M":100,"Qt8oEhjI":100,"DfxTckLr":100},"abilityState":{"entryOnce":{},"battleBond":{}},"weatherNegated":false}