{
  "c": "rdxaq1mP",
  "org": "no",
  "chp": 142,
  "ochp": -222,
  "ohp": 49,
  "ivs": {
    "hp": 16,
    "attack": 15,
    "defense": 17,
    "special_attack": 12,
    "special_defense": 22,
    "speed": 12
  },
  "evs": {
    "hp": 0,
    "attack": 0,
    "defense": 0,
    "special_attack": 0,
    "special_defense": 0,
    "speed": 0
  },
  "nat": "Adamant",
  "cpass": "46UZ4Zuh",
  "level": 19,
  "name": "cherubi",
  "omoves": [
    {
      "id": 33,
      "learn_method": "level-up",
      "level_learned_at": 1
    },
    {
      "id": 670,
      "learn_method": "level-up",
      "level_learned_at": 5
    }
  ],
  "ded": [],
  "ot": {
    "cherubi": -222
  },
  "symbol": "",
  "team": {
    "rdxaq1mP": 142,
    "5klmJG1W": 124,
    "SnJZzGbw": 161,
    "C1czvzzB": 111,
    "xPNmpDgC": 120,
    "V585CIwf": 114
  },
  "la": {
    "rdxaq1mP": 41,
    "5klmJG1W": 42,
    "SnJZzGbw": 50,
    "C1czvzzB": 44,
    "xPNmpDgC": 41,
    "V585CIwf": 38
  }
}