{"opass":"nZWZOhcF","c":"U8fbOPeQ","org":"no","chp":231,"ochp":0,"ohp":69,"ivs":{"hp":16,"attack":16,"defense":16,"special_attack":16,"special_defense":18,"speed":21},"evs":{"hp":0,"attack":0,"defense":0,"special_attack":0,"special_defense":0,"speed":0},"nat":"Lax","cpass":"Z5pbM4lc","level":32,"name":"dugtrio","oheld_item":"none","oability":"sand-force","omoves":[{"id":328,"learn_method":"level-up","level_learned_at":0},{"id":389,"learn_method":"level-up","level_learned_at":20},{"id":400,"learn_method":"level-up","level_learned_at":1},{"id":523,"learn_method":"level-up","level_learned_at":16}],"ded":[],"ot":{"dugtrio":0},"symbol":"","team":{"U8fbOPeQ":231,"XlOhxmFh":389,"04lmL5QN":355},"la":{"U8fbOPeQ":64,"XlOhxmFh":100,"04lmL5QN":98},"heldItems":{"U8fbOPeQ":"none","XlOhxmFh":"spooky-plate","04lmL5QN":"none","nZWZOhcF":"none"},"consumedHeldItems":{},"abilityState":{"entryOnce":{},"battleBond":{}},"weatherNegated":false,"statStages":{"U8fbOPeQ":{"attack":0,"defense":0,"special_attack":0,"special_defense":0,"speed":0,"accuracy":0,"evasion":0},"nZWZOhcF":{"attack":0,"defense":0,"special_attack":0,"special_defense":0,"speed":0,"accuracy":0,"evasion":0}}}