{"opass":"Jgs6Js1w","c":"FX99Jcan","org":"no","chp":187,"ochp":0,"ohp":59,"ivs":{"hp":28,"attack":10,"defense":10,"special_attack":16,"special_defense":21,"speed":19},"evs":{"hp":0,"attack":0,"defense":0,"special_attack":0,"special_defense":0,"speed":0},"nat":"Serious","cpass":"wJzUSHuv","level":25,"name":"pikachu","oability":"lightning-rod","omoves":[{"id":98,"learn_method":"level-up","level_learned_at":1},{"id":209,"learn_method":"level-up","level_learned_at":20},{"id":364,"learn_method":"level-up","level_learned_at":16},{"id":609,"learn_method":"level-up","level_learned_at":1}],"ded":[],"ot":{"pikachu":0},"symbol":"","team":{"FX99Jcan":187,"vecv1QVi":105,"f666Nykx":93,"cBzZilHm":160,"mLlgW3fe":123,"CXhkUq6p":142},"la":{"FX99Jcan":74,"vecv1QVi":31,"f666Nykx":38,"cBzZilHm":50,"mLlgW3fe":41,"CXhkUq6p":48},"abilityState":{"entryOnce":{},"battleBond":{}},"statStages":{"FX99Jcan":{"attack":0,"defense":0,"special_attack":0,"special_defense":0,"speed":0,"accuracy":0,"evasion":0},"Jgs6Js1w":{"attack":0,"defense":0,"special_attack":0,"special_defense":0,"speed":0,"accuracy":0,"evasion":0}}}