{"set":{"max_poke":6,"dual_type":true,"min_6l":0,"max_6l":6,"min_level":1,"max_level":100,"switch":true,"key_item":true,"sandbox":false,"random":false,"preview":"no","pin":false,"ban_types":[],"allow_types":[],"ban_regions":[],"allow_regions":[],"type_effects":true},"users":{"1335302812":true,"5242138546":true},"status":{},"statStages":{"1Z2AnQuA":{"attack":0,"defense":0,"special_attack":0,"special_defense":0,"speed":0,"accuracy":0,"evasion":0},"poYkMH2a":{"attack":0,"defense":0,"special_attack":0,"special_defense":0,"speed":0,"accuracy":0,"evasion":0}},"heldItems":{"1Z2AnQuA":"none","KI5D0snW":"none","9Dt8mmXo":"none","DDF81qpZ":"none","NvBNehwX":"life-orb","ofNBxSsf":"none","poYkMH2a":"choice-band","BhfloQjr":"choice-specs","qfQm5lQN":"none","AIUEJm8S":"none","7ec8BLAg":"choice-specs","FSMxgVfE":"none"},"consumedHeldItems":{},"c":"poYkMH2a","chp":349,"o":"1Z2AnQuA","ohp":264,"cid":"5242138546","oid":"1335302812","tem":{"poYkMH2a":349,"BhfloQjr":362,"qfQm5lQN":354,"AIUEJm8S":481,"7ec8BLAg":363,"FSMxgVfE":297},"la":{"poYkMH2a":100,"BhfloQjr":100,"qfQm5lQN":100,"AIUEJm8S":100,"7ec8BLAg":100,"FSMxgVfE":100},"tem2":{"1Z2AnQuA":264,"KI5D0snW":382,"9Dt8mmXo":404,"DDF81qpZ":337,"NvBNehwX":376,"ofNBxSsf":245},"la2":{"1Z2AnQuA":100,"KI5D0snW":100,"9Dt8mmXo":100,"DDF81qpZ":100,"NvBNehwX":100,"ofNBxSsf":65},"ot":{"undefined":264},"usedMoves":{},"abilityState":{"entryOnce":{},"battleBond":{}},"weatherNegated":false,"runs":[1335302812,5242138546]}