{"opass":"sMJidfAz","c":"AfrJyFT3","org":"no","chp":2,"ochp":0,"ohp":47,"ivs":{"hp":17,"attack":10,"defense":17,"special_attack":16,"special_defense":13,"speed":30},"evs":{"hp":0,"attack":0,"defense":0,"special_attack":0,"special_defense":0,"speed":0},"nat":"Bold","cpass":"4aivblah","level":21,"name":"shieldon","oability":"sturdy","omoves":[{"id":33,"learn_method":"level-up","level_learned_at":1},{"id":36,"learn_method":"level-up","level_learned_at":15}],"ded":[],"ot":{"shieldon":0},"symbol":"","team":{"AfrJyFT3":2,"USP6eG1Z":52,"i3Zbowkn":75,"YXw2z1Y1":116,"9jvifJC5":89,"E7dXyYp1":60},"la":{"AfrJyFT3":33,"USP6eG1Z":18,"i3Zbowkn":26,"YXw2z1Y1":35,"9jvifJC5":33,"E7dXyYp1":18},"abilityState":{"entryOnce":{},"battleBond":{}},"statStages":{"AfrJyFT3":{"attack":0,"defense":0,"special_attack":0,"special_defense":0,"speed":0,"accuracy":0,"evasion":0},"sMJidfAz":{"attack":0,"defense":0,"special_attack":0,"special_defense":0,"speed":0,"accuracy":0,"evasion":0}}}