{"opass":"n2c9jKrN","c":"QU99PvjF","org":"no","chp":172,"ochp":0,"ohp":127,"ivs":{"hp":19,"attack":19,"defense":23,"special_attack":10,"special_defense":18,"speed":14},"evs":{"hp":0,"attack":0,"defense":0,"special_attack":0,"special_defense":0,"speed":0},"nat":"Timid","cpass":"J8pBJkdV","level":41,"name":"empoleon","oability":"competitive","omoves":[{"id":61,"learn_method":"level-up","level_learned_at":19},{"id":31,"learn_method":"level-up","level_learned_at":28},{"id":362,"learn_method":"level-up","level_learned_at":33},{"id":250,"learn_method":"level-up","level_learned_at":39}],"ded":[],"ot":{"empoleon":0},"symbol":"","team":{"QU99PvjF":172,"3zK8PVU5":208},"la":{"QU99PvjF":55,"3zK8PVU5":60},"abilityState":{"entryOnce":{},"battleBond":{}},"statStages":{"QU99PvjF":{"attack":0,"defense":0,"special_attack":0,"special_defense":0,"speed":0,"accuracy":0,"evasion":0},"n2c9jKrN":{"attack":0,"defense":0,"special_attack":0,"special_defense":0,"speed":0,"accuracy":0,"evasion":0}}}