{"opass":"P826OXuL","c":"JzkZvmGw","org":"no","chp":9,"ochp":0,"ohp":33,"ivs":{"hp":14,"attack":19,"defense":18,"special_attack":18,"special_defense":17,"speed":14},"evs":{"hp":0,"attack":0,"defense":0,"special_attack":0,"special_defense":0,"speed":0},"nat":"Lonely","cpass":"hz32ykOL","level":13,"name":"doduo","oheld_item":"none","oability":"tangled-feet","omoves":[{"id":31,"learn_method":"level-up","level_learned_at":9},{"id":64,"learn_method":"level-up","level_learned_at":1},{"id":98,"learn_method":"level-up","level_learned_at":5}],"ded":[],"ot":{"doduo":0},"symbol":"","team":{"JzkZvmGw":9,"7hZGRvzp":98,"KZtAATeh":162,"CO9DkIVA":46,"QWDtYAAl":212},"la":{"JzkZvmGw":18,"7hZGRvzp":40,"KZtAATeh":50,"CO9DkIVA":10,"QWDtYAAl":61},"heldItems":{"JzkZvmGw":"none","7hZGRvzp":"none","KZtAATeh":"none","CO9DkIVA":"none","QWDtYAAl":"none","P826OXuL":"none"},"consumedHeldItems":{},"abilityState":{"entryOnce":{},"battleBond":{}},"weatherNegated":false,"statStages":{"JzkZvmGw":{"attack":0,"defense":0,"special_attack":0,"special_defense":0,"speed":0,"accuracy":0,"evasion":0},"P826OXuL":{"attack":0,"defense":0,"special_attack":0,"special_defense":0,"speed":0,"accuracy":0,"evasion":0}}}