{"opass":"sEKJXf3D","c":"WqtQdXQn","org":"no","chp":398,"ochp":0,"ohp":80,"ivs":{"hp":16,"attack":14,"defense":16,"special_attack":12,"special_defense":13,"speed":16},"evs":{"hp":0,"attack":0,"defense":0,"special_attack":0,"special_defense":0,"speed":0},"nat":"Bold","cpass":"3ACmhzdO","level":30,"name":"ivysaur","oability":"overgrow","omoves":[{"id":33,"learn_method":"level-up","level_learned_at":1},{"id":36,"learn_method":"level-up","level_learned_at":25},{"id":75,"learn_method":"level-up","level_learned_at":12},{"id":402,"learn_method":"level-up","level_learned_at":20}],"ded":[],"ot":{"ivysaur":0},"symbol":"","team":{"WqtQdXQn":398,"G0axX0Mj":58,"ABn0pQc2":82},"la":{"WqtQdXQn":100,"G0axX0Mj":22,"ABn0pQc2":30},"abilityState":{"entryOnce":{},"battleBond":{}},"statStages":{"WqtQdXQn":{"attack":0,"defense":0,"special_attack":0,"special_defense":0,"speed":0,"accuracy":0,"evasion":0},"sEKJXf3D":{"attack":0,"defense":0,"special_attack":0,"special_defense":0,"speed":0,"accuracy":0,"evasion":0}}}