{"opass":"TstjDTee","c":"1eLZ8bnv","org":"no","chp":137,"ochp":148,"ohp":148,"ivs":{"hp":16,"attack":18,"defense":22,"special_attack":24,"special_defense":26,"speed":27},"evs":{"hp":0,"attack":0,"defense":0,"special_attack":0,"special_defense":0,"speed":0},"nat":"Impish","cpass":"04pTIX7x","level":58,"name":"stakataka","oheld_item":"none","oability":"beast-boost","omoves":[{"id":23,"learn_method":"level-up","level_learned_at":15},{"id":33,"learn_method":"level-up","level_learned_at":1},{"id":88,"learn_method":"level-up","level_learned_at":5}],"ded":[],"ot":{"stakataka":148},"symbol":"","team":{"1eLZ8bnv":137,"DByCFqv8":185,"2tV5OwNS":95,"EjtCFOX0":103,"6UUYHSbq":174},"la":{"1eLZ8bnv":34,"DByCFqv8":47,"2tV5OwNS":33,"EjtCFOX0":29,"6UUYHSbq":49},"heldItems":{"1eLZ8bnv":"none","DByCFqv8":"none","2tV5OwNS":"none","EjtCFOX0":"none","6UUYHSbq":"none","TstjDTee":"none"},"consumedHeldItems":{},"abilityState":{"entryOnce":{},"battleBond":{}},"weatherNegated":false}