{
  "c": "ZpYcR2c0",
  "org": "no",
  "chp": 22,
  "ochp": -29,
  "ohp": 137,
  "ivs": {
    "hp": 11,
    "attack": 14,
    "defense": 15,
    "special_attack": 21,
    "special_defense": 21,
    "speed": 9
  },
  "evs": {
    "hp": 0,
    "attack": 0,
    "defense": 0,
    "special_attack": 0,
    "special_defense": 0,
    "speed": 0
  },
  "nat": "Gentle",
  "cpass": "LWIVOFar",
  "level": 41,
  "name": "azumarill",
  "omoves": [
    {
      "id": 340,
      "learn_method": "level-up",
      "level_learned_at": 15
    },
    {
      "id": 401,
      "learn_method": "level-up",
      "level_learned_at": 21
    },
    {
      "id": 583,
      "learn_method": "level-up",
      "level_learned_at": 25
    },
    {
      "id": 56,
      "learn_method": "level-up",
      "level_learned_at": 40
    }
  ],
  "ded": [],
  "ot": {
    "azumarill": -29
  },
  "symbol": "",
  "team": {
    "ZpYcR2c0": 22
  },
  "la": {
    "ZpYcR2c0": 30
  }
}