[{"user_id":1569248530,"data":{"pokes":[{"name":"charmander","id":4,"nature":"Serious","exp":135,"pass":"HopjjmIy","ivs":{"hp":7,"attack":0,"defense":0,"special_attack":11,"special_defense":23,"speed":5},"symbol":"","evs":{"hp":0,"attack":0,"defense":0,"special_attack":0,"special_defense":0,"speed":0},"moves":[10],"ability":"solar-power"}],"inv":{"pc":1,"region":"kanto","exp":0,"avtar":"1","template":"1","id":"grey","data":"black","hometown":"Kanto","name":"&#xD7;&#x35C;&#xD7;&#x1793;h&#xE19;&#xDF;h&#xD7;&#x35C;&#xD7;&#x1F940;&#x1F98B;&#x1FA90;","candy":0,"team":"1"},"balls":{"regular":10,"great":7,"ultra":3},"extra":{"pending":"5473934811","date":"22/02/2024","megas":{},"huntd":"2024-02-23","hunts":1,"rankRewards":{"claimedLevel":0,"lastClaimAtUtc":null},"rankLevel":1},"pokecaught":["charmander","arceus-rock","arceus-psychic"],"pokeseen":["charmander","arceus-rock","arceus-psychic","kangaskhan"],"teams":{"1":[],"2":[],"3":[],"4":[],"5":[],"6":[]},"settings":{"max_poke":6,"dual_type":true,"min_6l":0,"max_6l":6,"min_level":1,"max_level":100,"switch":true,"key_item":true,"sandbox":false,"random":false,"preview":"no","pin":false,"ban_types":[],"allow_types":[],"ban_regions":[],"allow_regions":[],"type_effects":true}},"reset":false}]