[{"user_id":1820668392,"data":{"pokes":[{"name":"bulbasaur","id":1,"nature":"Lonely","exp":2063,"pass":"idlQqROf","ivs":{"hp":6,"attack":0,"defense":4,"special_attack":21,"special_defense":23,"speed":18},"symbol":"","evs":{"hp":0,"attack":0,"defense":0,"special_attack":0,"special_defense":0,"speed":0},"moves":[33,75],"ability":"overgrow"},{"name":"articuno","nature":"Naughty","ivs":{"hp":28,"attack":16,"defense":22,"special_attack":18,"special_defense":23,"speed":18},"evs":{"hp":0,"attack":0,"defense":0,"special_attack":0,"special_defense":0,"speed":0},"moves":[420,246,573,58],"exp":175760,"id":144,"pass":"kLATDZX1","cpass":"w9rhOGms","symbol":"","ability":"pressure"},{"name":"seadra","nature":"Careful","ivs":{"hp":16,"attack":20,"defense":16,"special_attack":12,"special_defense":19,"speed":16},"evs":{"hp":0,"attack":0,"defense":0,"special_attack":0,"special_defense":0,"speed":0},"moves":[239,225,61,406],"exp":92018,"id":117,"pass":"XyXBd9Eu","cpass":"zYoWgPvB","symbol":"","ability":"sniper"},{"name":"charizard","nature":"Quiet","ivs":{"hp":16,"attack":13,"defense":10,"special_attack":17,"special_defense":22,"speed":21},"evs":{"hp":0,"attack":0,"defense":0,"special_attack":0,"special_defense":0,"speed":0},"moves":[225,424,163,53],"exp":90397,"id":6,"pass":"JWrV9pEd","cpass":"dDJIAztD","symbol":"","ability":"solar-power"},{"name":"moltres","nature":"Timid","ivs":{"hp":14,"attack":13,"defense":12,"special_attack":14,"special_defense":14,"speed":21},"evs":{"hp":0,"attack":0,"defense":0,"special_attack":3,"special_defense":0,"speed":0},"moves":[542,510,403,257],"exp":211187,"id":146,"pass":"X5f2NrUj","cpass":"XOD2zfY7","symbol":"","ability":"pressure"},{"name":"snorlax","nature":"Mild","ivs":{"hp":25,"attack":21,"defense":24,"special_attack":18,"special_defense":16,"speed":14},"evs":{"hp":0,"attack":0,"defense":0,"special_attack":0,"special_defense":0,"speed":3},"moves":[44,173,242,34],"exp":41889,"id":143,"pass":"jpU5o50h","cpass":"jCXW0CRU","symbol":"","ability":"thick-fat"},{"name":"kabutops","nature":"Quiet","ivs":{"hp":18,"attack":18,"defense":22,"special_attack":14,"special_defense":14,"speed":15},"evs":{"hp":0,"attack":0,"defense":0,"special_attack":0,"special_defense":0,"speed":0},"moves":[453,341,246,362],"exp":85783,"id":141,"pass":"SseW8FX6","cpass":"qELIZcJC","symbol":"","ability":"swift-swim"}],"inv":{"pc":4100,"region":"letsgo-kanto","exp":0,"avtar":"1","template":"1","id":"grey","data":"black","hometown":"Kanto","name":"Smriti","team":"2","candy":0,"lose":1},"balls":{"regular":10,"great":7,"ultra":10,"safari":0},"extra":{"date":"19/05/2024","megas":{},"huntd":"2024-05-23","hunts":45,"hunting":false,"saf":"Kanto","lastsafari":"2024-05-23","rankRewards":{"claimedLevel":0,"lastClaimAtUtc":null},"rankLevel":1},"settings":{"max_poke":6,"dual_type":true,"min_6l":0,"max_6l":6,"min_level":1,"max_level":100,"switch":true,"key_item":true,"sandbox":false,"random":false,"preview":"no","pin":false,"ban_types":[],"allow_types":[],"ban_regions":[],"allow_regions":[],"type_effects":true},"pokecaught":["bulbasaur","nidorino","seadra","charizard","moltres","snorlax","kabutops","articuno"],"pokeseen":["bulbasaur","nidorino","machop","porygon","seadra","kabutops","charizard","zapdos","articuno","moltres","mewtwo","snorlax"],"teams":{"1":["idlQqROf"],"2":["X5f2NrUj","XyXBd9Eu","SseW8FX6","JWrV9pEd","jpU5o50h","idlQqROf"],"3":[],"4":[],"5":[],"6":[]}},"reset":false}]