[{"user_id":5599392345,"data":{"pokes":[{"name":"froakie","id":656,"nature":"Calm","exp":135,"pass":"AzXTMaGN","ivs":{"hp":24,"attack":5,"defense":10,"special_attack":13,"special_defense":1,"speed":9},"symbol":"","evs":{"hp":0,"attack":0,"defense":0,"special_attack":0,"special_defense":0,"speed":0},"moves":[1],"ability":"torrent"}],"inv":{"pc":5000,"region":"kanto","exp":0,"avtar":"1","template":"1","id":"grey","data":"black","hometown":"Kalos","name":"&#x1D5D7;&#x1D5E2;&#x1D5E7; &#x3C5;","team":"1"},"balls":{"regular":10,"great":7,"ultra":3},"extra":{"date":"01/12/2024","megas":{},"refer":[1081483840,1264100203,1965550662],"huntd":"2024-12-01","hunts":4,"rankRewards":{"claimedLevel":0,"lastClaimAtUtc":null},"rankLevel":1},"settings":{"max_poke":6,"dual_type":true,"min_6l":0,"max_6l":6,"min_level":1,"max_level":100,"switch":true,"key_item":true,"sandbox":false,"random":false,"preview":"no","pin":false,"ban_types":[],"allow_types":[],"ban_regions":[],"allow_regions":[],"type_effects":true},"pokecaught":["froakie"],"pokeseen":["froakie"],"teams":{"1":["AzXTMaGN"],"2":[],"3":[],"4":[],"5":[],"6":[]}},"reset":false}]