[{"user_id":6454165193,"data":{"pokes":[{"name":"raboot","id":814,"nature":"Naughty","exp":12311,"pass":"uG4tEEVT","ivs":{"hp":10,"attack":18,"defense":5,"special_attack":17,"special_defense":23,"speed":21},"symbol":"","evs":{"hp":7,"attack":10,"defense":7,"special_attack":5,"special_defense":4,"speed":1},"moves":[33,488,98,24],"ability":"libero"},{"name":"regigigas","nature":"Naughty","ivs":{"hp":16,"attack":25,"defense":23,"special_attack":14,"special_defense":20,"speed":18},"evs":{"hp":0,"attack":0,"defense":0,"special_attack":0,"special_defense":0,"speed":0},"moves":[23,282,5,776],"exp":196830,"id":486,"pass":"3fZtgwxu","cpass":"K0N6Qtkk","symbol":"","ability":"slow-start"},{"name":"mewtwo","nature":"Naughty","ivs":{"hp":23,"attack":11,"defense":24,"special_attack":30,"special_defense":16,"speed":16},"evs":{"hp":0,"attack":2,"defense":0,"special_attack":0,"special_defense":0,"speed":0},"moves":[246,427,396,94],"exp":232949,"id":150,"pass":"r12kSNT3","cpass":"g5GOFmlx","symbol":"","ability":"pressure"},{"name":"dialga","nature":"Relaxed","ivs":{"hp":18,"attack":18,"defense":18,"special_attack":16,"special_defense":22,"speed":24},"evs":{"hp":0,"attack":0,"defense":0,"special_attack":0,"special_defense":0,"speed":0},"moves":[430,337,396,408],"exp":297910,"id":483,"pass":"02CM8eSv","cpass":"hZKfdxwK","symbol":"","ability":"telepathy"},{"name":"giratina-altered","nature":"Lax","ivs":{"hp":20,"attack":28,"defense":15,"special_attack":17,"special_defense":28,"speed":18},"evs":{"hp":0,"attack":0,"defense":0,"special_attack":0,"special_defense":0,"speed":0},"moves":[225,246,506,163],"exp":80000,"id":487,"pass":"lVutUUZm","cpass":"TP1N4Utj","symbol":"","ability":"pressure"},{"name":"marshtomp","nature":"Hasty","ivs":{"hp":15,"attack":17,"defense":21,"special_attack":16,"special_defense":17,"speed":10},"evs":{"hp":0,"attack":0,"defense":0,"special_attack":0,"special_defense":0,"speed":0},"moves":[57,89,249,88],"exp":2535,"id":259,"pass":"5ORK9HXx","cpass":"VkhPEs4p","symbol":"","ability":"torrent"},{"name":"palkia","nature":"Mild","ivs":{"hp":22,"attack":24,"defense":25,"special_attack":12,"special_defense":27,"speed":22},"evs":{"hp":0,"attack":0,"defense":0,"special_attack":0,"special_defense":0,"speed":0},"moves":[246,163,337,396],"exp":186096,"id":484,"pass":"Lzj6SLsS","cpass":"7SCoBrrp","symbol":"","ability":"pressure"},{"name":"gurdurr","nature":"Rash","ivs":{"hp":21,"attack":17,"defense":14,"special_attack":17,"special_defense":15,"speed":15},"evs":{"hp":0,"attack":0,"defense":0,"special_attack":0,"special_defense":0,"speed":0},"moves":[88,157,21,223],"exp":61450,"id":533,"pass":"NAFZbyR1","cpass":"b2LBssU3","symbol":"","ability":"sheer-force"},{"name":"arceus","nature":"Bold","ivs":{"hp":25,"attack":23,"defense":25,"special_attack":30,"special_defense":23,"speed":27},"evs":{"hp":153,"attack":1,"defense":143,"special_attack":109,"special_defense":103,"speed":0},"moves":[414,63,44913,248],"exp":1250000,"id":493,"pass":"BWhOdvXQ","cpass":"eba5qHnr","symbol":"","ability":"multitype"},{"name":"mewtwo","nature":"Hasty","ivs":{"hp":20,"attack":22,"defense":15,"special_attack":26,"special_defense":19,"speed":27},"evs":{"hp":0,"attack":0,"defense":0,"special_attack":60,"special_defense":198,"speed":252},"moves":[246,427,396,248],"exp":1250000,"id":150,"pass":"4Q1TWlrM","cpass":"gTFMDiZ4","symbol":"","ability":"unnerve"},{"name":"bisharp","nature":"Rash","ivs":{"hp":15,"attack":14,"defense":13,"special_attack":15,"special_defense":12,"speed":20},"evs":{"hp":0,"attack":0,"defense":0,"special_attack":0,"special_defense":0,"speed":0},"moves":[372,163,400,442],"exp":205379,"id":625,"pass":"21fSasZN","cpass":"JuBkWcpr","symbol":"","ability":"defiant"},{"name":"aerodactyl","nature":"Sassy","ivs":{"hp":16,"attack":23,"defense":14,"special_attack":15,"special_defense":18,"speed":19},"evs":{"hp":0,"attack":0,"defense":0,"special_attack":0,"special_defense":0,"speed":0},"moves":[44,246],"exp":156,"id":142,"pass":"dypzueAN","cpass":"nhSqlhcz","symbol":"","ability":"pressure"},{"name":"gible","nature":"Gentle","ivs":{"hp":9,"attack":20,"defense":14,"special_attack":11,"special_defense":15,"speed":16},"evs":{"hp":0,"attack":0,"defense":0,"special_attack":0,"special_defense":0,"speed":0},"moves":[33,328,225],"exp":7290,"id":443,"pass":"Ivjhc7o2","cpass":"xWdqFahX","symbol":"","ability":"sand-veil"},{"name":"lugia","nature":"Mild","ivs":{"hp":22,"attack":27,"defense":25,"special_attack":14,"special_defense":17,"speed":18},"evs":{"hp":0,"attack":0,"defense":0,"special_attack":0,"special_defense":0,"speed":0},"moves":[246,311,407,326],"exp":63316,"id":249,"pass":"qOZFMIdW","cpass":"MYyBheYz","symbol":"","ability":"multiscale"},{"name":"rockruff","nature":"Bold","ivs":{"hp":17,"attack":15,"defense":20,"special_attack":11,"special_defense":13,"speed":12},"evs":{"hp":0,"attack":0,"defense":0,"special_attack":0,"special_defense":0,"speed":0},"moves":[33],"exp":1728,"id":744,"pass":"oup3CnRz","cpass":"sgn2KhTK","symbol":"","ability":"keen-eye"},{"name":"aerodactyl","nature":"Rash","ivs":{"hp":17,"attack":13,"defense":13,"special_attack":19,"special_defense":14,"speed":18},"evs":{"hp":0,"attack":0,"defense":0,"special_attack":0,"special_defense":0,"speed":0},"moves":[44,246,17],"exp":2746,"id":142,"pass":"78MeZNig","cpass":"8gDIU2xs","symbol":"","ability":"rock-head"},{"name":"absol","nature":"Relaxed","ivs":{"hp":16,"attack":23,"defense":28,"special_attack":18,"special_defense":21,"speed":16},"evs":{"hp":0,"attack":0,"defense":0,"special_attack":0,"special_defense":0,"speed":0},"moves":[98,282],"exp":6458,"id":359,"pass":"3A4iaGGo","cpass":"qg5kMZV0","symbol":"","ability":"pressure"},{"name":"kyurem-black","nature":"Quiet","ivs":{"hp":21,"attack":22,"defense":16,"special_attack":30,"special_defense":21,"speed":24},"evs":{"hp":0,"attack":0,"defense":0,"special_attack":0,"special_defense":0,"speed":0},"moves":[163,406,58,304],"exp":106480,"id":646,"pass":"5VDlcr6a","cpass":"1ISAI7Bs","symbol":"","ability":"teravolt"},{"name":"buneary","nature":"Quiet","ivs":{"hp":23,"attack":16,"defense":16,"special_attack":12,"special_defense":8,"speed":15},"evs":{"hp":0,"attack":0,"defense":0,"special_attack":0,"special_defense":0,"speed":0},"moves":[1],"exp":2744,"id":427,"pass":"LdOvcoNR","cpass":"ONmKudxB","symbol":"","ability":"klutz"},{"name":"ralts","nature":"Calm","ivs":{"hp":8,"attack":7,"defense":10,"special_attack":13,"special_defense":9,"speed":17},"evs":{"hp":0,"attack":0,"defense":0,"special_attack":0,"special_defense":0,"speed":0},"moves":[574,93],"exp":1663,"id":280,"pass":"74Bct6CN","cpass":"savCQB9L","symbol":"","ability":"synchronize"},{"name":"kirlia","nature":"Modest","ivs":{"hp":19,"attack":14,"defense":20,"special_attack":13,"special_defense":14,"speed":13},"evs":{"hp":1,"attack":3,"defense":3,"special_attack":5,"special_defense":0,"speed":1},"moves":[574,93,577,60],"exp":10164,"id":281,"pass":"44xRMb2N","cpass":"m24Mhzfz","symbol":"","ability":"trace"},{"name":"gardevoir","nature":"Serious","ivs":{"hp":18,"attack":20,"defense":14,"special_attack":18,"special_defense":12,"speed":12},"evs":{"hp":5,"attack":2,"defense":5,"special_attack":4,"special_defense":0,"speed":3},"moves":[93,574,605,60],"exp":34464,"id":282,"pass":"KPqkzxvy","cpass":"L3vIHPdF","symbol":"","ability":"telepathy"},{"name":"pikachu-hoenn-cap","nature":"Hasty","ivs":{"hp":20,"attack":18,"defense":15,"special_attack":23,"special_defense":19,"speed":16},"evs":{"hp":0,"attack":0,"defense":0,"special_attack":0,"special_defense":0,"speed":0},"moves":[84,98,609,364],"exp":6859,"id":25,"pass":"KAX7j3qs","cpass":"PCC8DWKa","symbol":"","ability":"static"},{"name":"gible","nature":"Naive","ivs":{"hp":16,"attack":17,"defense":18,"special_attack":21,"special_defense":16,"speed":14},"evs":{"hp":0,"attack":0,"defense":0,"special_attack":0,"special_defense":0,"speed":0},"moves":[33,328,225,523],"exp":8573,"id":443,"pass":"6YYZOhJ4","cpass":"jf04vbtj","symbol":"","ability":"rough-skin"},{"name":"kyurem-black","nature":"Lax","ivs":{"hp":27,"attack":24,"defense":16,"special_attack":17,"special_defense":23,"speed":17},"evs":{"hp":0,"attack":0,"defense":0,"special_attack":0,"special_defense":0,"speed":0},"moves":[246,573,163,406],"exp":37238,"id":646,"pass":"nlTijAq4","cpass":"J53kBTB2","symbol":"","ability":"teravolt"},{"name":"abra","nature":"Lonely","ivs":{"hp":19,"attack":21,"defense":25,"special_attack":15,"special_defense":19,"speed":21},"evs":{"hp":0,"attack":0,"defense":0,"special_attack":0,"special_defense":0,"speed":0},"moves":[165],"exp":314,"id":63,"pass":"fCWYY1Rb","cpass":"rppvRSj8","symbol":"","ability":"synchronize"},{"name":"starly","nature":"Serious","ivs":{"hp":11,"attack":14,"defense":16,"special_attack":12,"special_defense":13,"speed":18},"evs":{"hp":0,"attack":0,"defense":0,"special_attack":0,"special_defense":0,"speed":0},"moves":[33],"exp":135,"id":396,"pass":"ZwWTjABJ","cpass":"JbqXTElS","symbol":"","ability":"keen-eye"},{"name":"regigigas","nature":"Naughty","ivs":{"hp":22,"attack":29,"defense":20,"special_attack":23,"special_defense":22,"speed":20},"evs":{"hp":132,"attack":195,"defense":180,"special_attack":0,"special_defense":0,"speed":0},"moves":[428,282,416,359],"exp":1250000,"id":486,"pass":"59KGnSdJ","cpass":"wFmZmPbE","symbol":"","ability":"slow-start"},{"name":"starly","nature":"Adamant","ivs":{"hp":18,"attack":17,"defense":20,"special_attack":20,"special_defense":21,"speed":10},"evs":{"hp":0,"attack":0,"defense":0,"special_attack":0,"special_defense":0,"speed":0},"moves":[33,98],"exp":419,"id":396,"pass":"mVipByeR","cpass":"ATOlkmRS","symbol":"","ability":"keen-eye"},{"name":"riolu","nature":"Naughty","ivs":{"hp":20,"attack":17,"defense":17,"special_attack":13,"special_defense":28,"speed":16},"evs":{"hp":0,"attack":0,"defense":0,"special_attack":0,"special_defense":0,"speed":0},"moves":[98,364,232],"exp":5460,"id":447,"pass":"aoVPYjyq","cpass":"6CjR3soP","symbol":"","ability":"prankster"},{"name":"wimpod","nature":"Naughty","ivs":{"hp":15,"attack":28,"defense":21,"special_attack":21,"special_defense":20,"speed":19},"evs":{"hp":0,"attack":0,"defense":0,"special_attack":0,"special_defense":0,"speed":0},"moves":[522],"exp":343,"id":767,"pass":"ORffP32e","cpass":"TiWAttyA","symbol":"","ability":"wimp-out"},{"name":"nincada","nature":"Quiet","ivs":{"hp":30,"attack":13,"defense":16,"special_attack":17,"special_defense":15,"speed":18},"evs":{"hp":0,"attack":0,"defense":0,"special_attack":0,"special_defense":0,"speed":0},"moves":[10,206],"exp":3041,"id":290,"pass":"PtxAP3Ci","cpass":"Ep26yG2D","symbol":"","ability":"compound-eyes"},{"name":"kyurem-black","nature":"Modest","ivs":{"hp":19,"attack":18,"defense":19,"special_attack":25,"special_defense":27,"speed":27},"evs":{"hp":0,"attack":0,"defense":0,"special_attack":0,"special_defense":0,"speed":0},"moves":[58,304,559,59],"exp":243890,"id":646,"pass":"JRvIYT5f","cpass":"EUqiQ4p8","symbol":"","ability":"teravolt"},{"name":"rufflet","nature":"Timid","ivs":{"hp":10,"attack":15,"defense":16,"special_attack":19,"special_defense":16,"speed":16},"evs":{"hp":0,"attack":0,"defense":0,"special_attack":0,"special_defense":0,"speed":0},"moves":[64,17],"exp":11576,"id":627,"pass":"XkBXiyL0","cpass":"jQPUktMN","symbol":"","ability":"sheer-force"},{"name":"rufflet","nature":"Timid","ivs":{"hp":10,"attack":15,"defense":16,"special_attack":19,"special_defense":16,"speed":16},"evs":{"hp":0,"attack":0,"defense":0,"special_attack":0,"special_defense":0,"speed":0},"moves":[64,17],"exp":11576,"id":627,"pass":"Qf9Ept87","cpass":"jQPUktMN","symbol":"","ability":"keen-eye"},{"name":"wimpod","nature":"Serious","ivs":{"hp":30,"attack":18,"defense":23,"special_attack":15,"special_defense":17,"speed":26},"evs":{"hp":0,"attack":0,"defense":0,"special_attack":0,"special_defense":0,"speed":0},"moves":[522],"exp":2197,"id":767,"pass":"6rQCH8P9","cpass":"SYRoA7Zz","symbol":"","ability":"wimp-out"},{"name":"dialga","nature":"Lax","ivs":{"hp":19,"attack":20,"defense":19,"special_attack":20,"special_defense":22,"speed":22},"evs":{"hp":0,"attack":0,"defense":0,"special_attack":0,"special_defense":0,"speed":0},"moves":[163,430,337,396],"exp":219520,"id":483,"pass":"qiVBfRZF","cpass":"2FKIx4Kz","symbol":"","ability":"telepathy"},{"name":"torchic","nature":"Mild","ivs":{"hp":19,"attack":17,"defense":8,"special_attack":17,"special_defense":15,"speed":19},"evs":{"hp":0,"attack":0,"defense":0,"special_attack":0,"special_defense":0,"speed":0},"moves":[10,52,98,488],"exp":742,"id":255,"pass":"6xkgLo8V","cpass":"SQFNJJtH","symbol":"","ability":"blaze"},{"name":"vigoroth","nature":"Lax","ivs":{"hp":15,"attack":18,"defense":25,"special_attack":21,"special_defense":16,"speed":21},"evs":{"hp":0,"attack":0,"defense":0,"special_attack":0,"special_defense":0,"speed":0},"moves":[253,154,163,498],"exp":33750,"id":288,"pass":"PcEbnQfh","cpass":"FZhfydEp","symbol":"","ability":"vital-spirit"},{"name":"squirtle","nature":"Rash","ivs":{"hp":14,"attack":18,"defense":11,"special_attack":22,"special_defense":20,"speed":12},"evs":{"hp":0,"attack":0,"defense":0,"special_attack":0,"special_defense":0,"speed":0},"moves":[33,55,229,44],"exp":1261,"id":7,"pass":"5NFAOad2","cpass":"p8pkpiL4","symbol":"","ability":"torrent"},{"name":"chespin","nature":"Adamant","ivs":{"hp":12,"attack":19,"defense":15,"special_attack":16,"special_defense":14,"speed":23},"evs":{"hp":0,"attack":0,"defense":0,"special_attack":0,"special_defense":0,"speed":0},"moves":[22],"exp":135,"id":650,"pass":"cDqwzEMm","cpass":"b9GOD3O0","symbol":"","ability":"overgrow"},{"name":"golett","nature":"Brave","ivs":{"hp":12,"attack":15,"defense":21,"special_attack":16,"special_defense":20,"speed":14},"evs":{"hp":0,"attack":0,"defense":0,"special_attack":0,"special_defense":0,"speed":0},"moves":[189,310,1,325],"exp":2744,"id":622,"pass":"4uA7gfqc","cpass":"bi3Cn0TD","symbol":"","ability":"klutz"},{"name":"slakoth","nature":"Quirky","ivs":{"hp":18,"attack":17,"defense":24,"special_attack":22,"special_defense":12,"speed":17},"evs":{"hp":0,"attack":0,"defense":0,"special_attack":0,"special_defense":0,"speed":0},"moves":[10],"exp":640,"id":287,"pass":"DxdAIXkN","cpass":"zTBqA4dQ","symbol":"","ability":"truant"},{"name":"slakoth","nature":"Quirky","ivs":{"hp":18,"attack":17,"defense":24,"special_attack":22,"special_defense":12,"speed":17},"evs":{"hp":0,"attack":0,"defense":0,"special_attack":0,"special_defense":0,"speed":0},"moves":[10],"exp":640,"id":287,"pass":"4teUsard","cpass":"zTBqA4dQ","symbol":"","ability":"truant"},{"name":"bulbasaur","nature":"Impish","ivs":{"hp":16,"attack":14,"defense":13,"special_attack":17,"special_defense":12,"speed":14},"evs":{"hp":0,"attack":0,"defense":0,"special_attack":0,"special_defense":0,"speed":0},"moves":[33,22],"exp":179,"id":1,"pass":"SAA4l6aT","cpass":"8UE56sO1","symbol":"","ability":"overgrow"},{"name":"spectrier","nature":"Quiet","ivs":{"hp":17,"attack":29,"defense":20,"special_attack":28,"special_defense":28,"speed":23},"evs":{"hp":0,"attack":0,"defense":0,"special_attack":0,"special_defense":0,"speed":0},"moves":[506,23,247,36],"exp":175760,"id":897,"pass":"1cxAaFrj","cpass":"MIg4qqwE","symbol":"","ability":"grim-neigh"},{"name":"voltorb","nature":"Quirky","ivs":{"hp":20,"attack":13,"defense":24,"special_attack":18,"special_defense":15,"speed":22},"evs":{"hp":0,"attack":0,"defense":0,"special_attack":0,"special_defense":0,"speed":0},"moves":[33],"exp":216,"id":100,"pass":"8ONPaplt","cpass":"muPuoJ8v","symbol":"","ability":"static"},{"name":"abra","nature":"Naive","ivs":{"hp":19,"attack":21,"defense":15,"special_attack":21,"special_defense":11,"speed":16},"evs":{"hp":0,"attack":0,"defense":0,"special_attack":0,"special_defense":0,"speed":0},"moves":[165],"exp":314,"id":63,"pass":"EmxXYe1P","cpass":"XxfvwI0V","symbol":"","ability":"inner-focus"},{"name":"mankey","nature":"Sassy","ivs":{"hp":21,"attack":20,"defense":17,"special_attack":14,"special_defense":18,"speed":24},"evs":{"hp":0,"attack":0,"defense":0,"special_attack":0,"special_defense":0,"speed":0},"moves":[10,343,154,2],"exp":729,"id":56,"pass":"AoOS1Vfg","cpass":"b5tB58Ea","symbol":"","ability":"defiant"},{"name":"voltorb","nature":"Careful","ivs":{"hp":24,"attack":14,"defense":25,"special_attack":30,"special_defense":12,"speed":22},"evs":{"hp":0,"attack":0,"defense":0,"special_attack":0,"special_defense":0,"speed":0},"moves":[33,209],"exp":1331,"id":100,"pass":"1FwbtqP6","cpass":"oeScxjoq","symbol":"","ability":"aftermath"},{"name":"palkia","nature":"Quirky","ivs":{"hp":18,"attack":19,"defense":21,"special_attack":14,"special_defense":27,"speed":21},"evs":{"hp":0,"attack":0,"defense":0,"special_attack":0,"special_defense":0,"speed":0},"moves":[163,337,396,408],"exp":312558,"id":484,"pass":"Vc5Jw3Bu","cpass":"SPdf4c5J","symbol":"","ability":"telepathy"},{"name":"guzzlord","nature":"Mild","ivs":{"hp":30,"attack":23,"defense":25,"special_attack":23,"special_defense":17,"speed":30},"evs":{"hp":0,"attack":0,"defense":0,"special_attack":0,"special_defense":0,"speed":0},"moves":[707,242,34,359],"exp":207968,"id":799,"pass":"ZHuUKIp9","cpass":"8zmQp0Eh","symbol":"","ability":"beast-boost"},{"name":"naganadel","nature":"Careful","ivs":{"hp":14,"attack":22,"defense":20,"special_attack":15,"special_defense":20,"speed":20},"evs":{"hp":0,"attack":0,"defense":0,"special_attack":0,"special_defense":0,"speed":0},"moves":[31,565,474,398],"exp":175760,"id":804,"pass":"NwK2JJKF","cpass":"unjFeHoD","symbol":"","ability":"beast-boost"},{"name":"marshadow","nature":"Rash","ivs":{"hp":15,"attack":19,"defense":23,"special_attack":12,"special_defense":22,"speed":23},"evs":{"hp":0,"attack":0,"defense":0,"special_attack":0,"special_defense":0,"speed":0},"moves":[395,372,389,409],"exp":312558,"id":802,"pass":"5RZqMa1U","cpass":"nXlvkkB0","symbol":"","ability":"technician"},{"name":"lycanroc-midnight","nature":"Bold","ivs":{"hp":25,"attack":22,"defense":18,"special_attack":21,"special_defense":25,"speed":14},"evs":{"hp":0,"attack":0,"defense":0,"special_attack":0,"special_defense":0,"speed":0},"moves":[33,88],"exp":5832,"id":745,"pass":"dCy5gs4Y","cpass":"EGPjHino","symbol":"","ability":"keen-eye"},{"name":"rockruff-own-tempo","nature":"Adamant","ivs":{"hp":22,"attack":15,"defense":13,"special_attack":20,"special_defense":16,"speed":17},"evs":{"hp":0,"attack":0,"defense":0,"special_attack":0,"special_defense":0,"speed":0},"moves":[33,88,44],"exp":9261,"id":744,"pass":"doDxTMF7","cpass":"IQ3ZBKs1","symbol":"","ability":"own-tempo"},{"name":"flabebe-yellow","nature":"Calm","ivs":{"hp":17,"attack":25,"defense":9,"special_attack":19,"special_defense":16,"speed":12},"evs":{"hp":0,"attack":0,"defense":0,"special_attack":0,"special_defense":0,"speed":0},"moves":[22,33,584,75],"exp":6881,"id":669,"pass":"1v0N040H","cpass":"VdAgP4Wx","symbol":"","ability":"symbiosis"},{"name":"magearna","nature":"Brave","ivs":{"hp":21,"attack":30,"defense":24,"special_attack":28,"special_defense":22,"speed":20},"evs":{"hp":0,"attack":0,"defense":0,"special_attack":0,"special_defense":0,"speed":0},"moves":[205,60,62,442],"exp":327680,"id":801,"pass":"AvE8AIM1","cpass":"mQbMImUJ","symbol":"","ability":"soul-heart"},{"name":"solgaleo","nature":"Jolly","ivs":{"hp":15,"attack":16,"defense":24,"special_attack":23,"special_defense":20,"speed":15},"evs":{"hp":0,"attack":0,"defense":0,"special_attack":0,"special_defense":0,"speed":0},"moves":[430,428,242,528],"exp":243890,"id":791,"pass":"vJWleBK0","cpass":"G2qyqtQh","symbol":"","ability":"full-metal-body"},{"name":"kartana","nature":"Hasty","ivs":{"hp":21,"attack":18,"defense":20,"special_attack":19,"special_defense":17,"speed":19},"evs":{"hp":0,"attack":0,"defense":0,"special_attack":0,"special_defense":0,"speed":0},"moves":[15,314,332,400],"exp":207968,"id":798,"pass":"VaCupN2N","cpass":"oYY8NvTv","symbol":"","ability":"beast-boost"},{"name":"celebi","nature":"Quiet","ivs":{"hp":26,"attack":24,"defense":19,"special_attack":17,"special_defense":30,"speed":20},"evs":{"hp":0,"attack":0,"defense":0,"special_attack":0,"special_defense":0,"speed":0},"moves":[93,345,246],"exp":52127,"id":251,"pass":"DiVz0X9T","cpass":"z2ZH4nA2","symbol":"","ability":"natural-cure"},{"name":"groudon","nature":"Careful","ivs":{"hp":19,"attack":24,"defense":27,"special_attack":15,"special_defense":25,"speed":25},"evs":{"hp":0,"attack":0,"defense":0,"special_attack":0,"special_defense":0,"speed":0},"moves":[436,414,89,359],"exp":256723,"id":383,"pass":"RmEbwXJH","cpass":"gy5ymdV1","symbol":"","ability":"drought"},{"name":"rufflet","nature":"Adamant","ivs":{"hp":10,"attack":15,"defense":7,"special_attack":9,"special_defense":7,"speed":13},"evs":{"hp":0,"attack":0,"defense":0,"special_attack":0,"special_defense":0,"speed":0},"moves":[64,17],"exp":3430,"id":627,"pass":"Y48r89GK","cpass":"tFTnZDOs","symbol":"","ability":"sheer-force"},{"name":"kyurem-black","nature":"Rash","ivs":{"hp":16,"attack":22,"defense":19,"special_attack":22,"special_defense":28,"speed":22},"evs":{"hp":0,"attack":0,"defense":0,"special_attack":0,"special_defense":0,"speed":0},"moves":[163,406,58,304],"exp":106480,"id":646,"pass":"EnsHE6dh","cpass":"Ck8trXpP","symbol":"","ability":"teravolt"},{"name":"bellsprout","nature":"Calm","ivs":{"hp":8,"attack":6,"defense":4,"special_attack":5,"special_defense":7,"speed":7},"evs":{"hp":0,"attack":0,"defense":0,"special_attack":0,"special_defense":0,"speed":0},"moves":[22,35],"exp":4431,"id":69,"pass":"aahOIybd","cpass":"JKVfAZwH","symbol":"","ability":"gluttony"},{"name":"buneary","nature":"Mild","ivs":{"hp":15,"attack":15,"defense":13,"special_attack":10,"special_defense":10,"speed":21},"evs":{"hp":0,"attack":0,"defense":0,"special_attack":0,"special_defense":0,"speed":0},"moves":[1],"exp":216,"id":427,"pass":"f4qcq2j4","cpass":"J9I5RaHR","symbol":"","ability":"klutz"},{"name":"pikachu-unova-cap","nature":"Lonely","ivs":{"hp":19,"attack":20,"defense":19,"special_attack":22,"special_defense":20,"speed":29},"evs":{"hp":0,"attack":0,"defense":0,"special_attack":0,"special_defense":0,"speed":0},"moves":[98,609,364,209],"exp":12167,"id":25,"pass":"elxXoLo9","cpass":"8vjxlNCm","symbol":"","ability":"static"},{"name":"chinchou","nature":"Quiet","ivs":{"hp":13,"attack":25,"defense":15,"special_attack":13,"special_defense":16,"speed":13},"evs":{"hp":0,"attack":0,"defense":0,"special_attack":0,"special_defense":0,"speed":0},"moves":[55,61,209],"exp":15208,"id":170,"pass":"xs6qrsCF","cpass":"6dHi1e7m","symbol":"","ability":"illuminate"},{"name":"doduo","nature":"Lax","ivs":{"hp":10,"attack":30,"defense":25,"special_attack":24,"special_defense":18,"speed":20},"evs":{"hp":0,"attack":0,"defense":0,"special_attack":0,"special_defense":0,"speed":0},"moves":[64,98,99,31],"exp":2744,"id":84,"pass":"tj2tU8Gc","cpass":"E90xquMc","symbol":"","ability":"run-away"},{"name":"shroomish","nature":"Serious","ivs":{"hp":18,"attack":24,"defense":19,"special_attack":19,"special_defense":29,"speed":16},"evs":{"hp":0,"attack":0,"defense":0,"special_attack":0,"special_defense":0,"speed":0},"moves":[33,71],"exp":178,"id":285,"pass":"NAayE87z","cpass":"35ReAz5r","symbol":"","ability":"effect-spore"},{"name":"magikarp","nature":"Calm","ivs":{"hp":16,"attack":22,"defense":13,"special_attack":15,"special_defense":17,"speed":26},"evs":{"hp":0,"attack":0,"defense":0,"special_attack":0,"special_defense":0,"speed":0},"moves":[165,33],"exp":6141,"id":129,"pass":"KN0QGuOj","cpass":"eQRnJsny","symbol":"","ability":"swift-swim"},{"name":"buneary","nature":"Naive","ivs":{"hp":12,"attack":17,"defense":14,"special_attack":18,"special_defense":15,"speed":12},"evs":{"hp":0,"attack":0,"defense":0,"special_attack":0,"special_defense":0,"speed":0},"moves":[1],"exp":2197,"id":427,"pass":"nZPagPQj","cpass":"NfS0gqfK","symbol":"","ability":"run-away"},{"name":"nidoran-m","nature":"Careful","ivs":{"hp":4,"attack":2,"defense":9,"special_attack":8,"special_defense":6,"speed":1},"evs":{"hp":0,"attack":0,"defense":0,"special_attack":0,"special_defense":0,"speed":0},"moves":[40,64],"exp":314,"id":32,"pass":"NB8Lz2Cg","cpass":"Mut1UrDj","symbol":"","ability":"poison-point"},{"name":"charmander","id":4,"nature":"Sassy","exp":135,"pass":"xlSbEl5C","ivs":{"hp":16,"attack":3,"defense":23,"special_attack":6,"special_defense":10,"speed":3},"symbol":"","evs":{"hp":0,"attack":0,"defense":0,"special_attack":0,"special_defense":0,"speed":0},"moves":[52],"ability":"solar-power"},{"name":"kyurem-white","nature":"Lax","ivs":{"hp":15,"attack":19,"defense":20,"special_attack":14,"special_defense":22,"speed":25},"evs":{"hp":0,"attack":0,"defense":0,"special_attack":0,"special_defense":0,"speed":0},"moves":[246,573,163,406],"exp":33750,"id":646,"pass":"iikwRcEQ","cpass":"f5OXV1fF","symbol":"","ability":"turboblaze"},{"name":"staryu","nature":"Sassy","ivs":{"hp":9,"attack":23,"defense":15,"special_attack":23,"special_defense":11,"speed":24},"evs":{"hp":0,"attack":0,"defense":0,"special_attack":0,"special_defense":0,"speed":0},"moves":[33,55,229],"exp":4218,"id":120,"pass":"yvVvrwha","cpass":"oFTCbVGM","symbol":"","ability":"illuminate"},{"name":"mewtwo","nature":"Sassy","ivs":{"hp":22,"attack":30,"defense":24,"special_attack":18,"special_defense":14,"speed":25},"evs":{"hp":0,"attack":0,"defense":0,"special_attack":0,"special_defense":0,"speed":0},"moves":[246,427,396,94],"exp":243890,"id":150,"pass":"Vhja9Bnk","cpass":"SkP8gSWL","symbol":"","ability":"pressure"},{"name":"yveltal","nature":"Adamant","ivs":{"hp":12,"attack":25,"defense":23,"special_attack":19,"special_defense":21,"speed":23},"evs":{"hp":2,"attack":150,"defense":151,"special_attack":2,"special_defense":4,"speed":2},"moves":[403,492,94,613],"exp":328438,"id":717,"pass":"Zl10eLU8","cpass":"PHCPC0iy","symbol":"","ability":"dark-aura"},{"name":"slakoth","nature":"Naughty","ivs":{"hp":8,"attack":5,"defense":7,"special_attack":1,"special_defense":4,"speed":11},"evs":{"hp":0,"attack":0,"defense":0,"special_attack":0,"special_defense":0,"speed":0},"moves":[10],"exp":640,"id":287,"pass":"rdKwAAKs","cpass":"FAh5w5Hc","symbol":"","ability":"truant"},{"name":"wurmple","nature":"Sassy","ivs":{"hp":12,"attack":12,"defense":13,"special_attack":17,"special_defense":16,"speed":21},"evs":{"hp":0,"attack":0,"defense":0,"special_attack":0,"special_defense":0,"speed":0},"moves":[33,40],"exp":216,"id":265,"pass":"9Sr6m9hF","cpass":"65Y4N8SZ","symbol":"","ability":"shield-dust"},{"name":"magikarp","nature":"Rash","ivs":{"hp":17,"attack":16,"defense":13,"special_attack":21,"special_defense":17,"speed":15},"evs":{"hp":0,"attack":0,"defense":0,"special_attack":0,"special_defense":0,"speed":0},"moves":[165,33],"exp":8573,"id":129,"pass":"WrrVN6TC","cpass":"lNBUP3dn","symbol":"","ability":"swift-swim"},{"name":"slakoth","nature":"Naughty","ivs":{"hp":16,"attack":13,"defense":16,"special_attack":15,"special_defense":18,"speed":20},"evs":{"hp":0,"attack":0,"defense":0,"special_attack":0,"special_defense":0,"speed":0},"moves":[10],"exp":1663,"id":287,"pass":"nlQzinve","cpass":"ljaF8oFC","symbol":"","ability":"truant"},{"name":"silcoon","nature":"Jolly","ivs":{"hp":12,"attack":8,"defense":17,"special_attack":13,"special_defense":18,"speed":13},"evs":{"hp":0,"attack":0,"defense":0,"special_attack":0,"special_defense":0,"speed":0},"moves":[165],"exp":343,"id":266,"pass":"R13VzAWH","cpass":"4fELFnpq","symbol":"","ability":"shed-skin"},{"name":"magikarp","nature":"Bold","ivs":{"hp":16,"attack":12,"defense":16,"special_attack":13,"special_defense":12,"speed":23},"evs":{"hp":0,"attack":0,"defense":0,"special_attack":0,"special_defense":0,"speed":0},"moves":[165],"exp":1663,"id":129,"pass":"kpGXBhYK","cpass":"vYiLqU97","symbol":"","ability":"rattled"},{"name":"celebi","nature":"Relaxed","ivs":{"hp":24,"attack":24,"defense":22,"special_attack":20,"special_defense":20,"speed":16},"evs":{"hp":0,"attack":0,"defense":0,"special_attack":0,"special_defense":0,"speed":0},"moves":[93,345,246],"exp":29949,"id":251,"pass":"Kc17Cx2l","cpass":"DeJ1b67F","symbol":"","ability":"natural-cure"},{"name":"silcoon","nature":"Quirky","ivs":{"hp":20,"attack":18,"defense":17,"special_attack":26,"special_defense":26,"speed":22},"evs":{"hp":0,"attack":0,"defense":0,"special_attack":0,"special_defense":0,"speed":0},"moves":[165],"exp":512,"id":266,"pass":"NAe4bzzP","cpass":"V4Isk3j9","symbol":"","ability":"shed-skin"},{"name":"magikarp","nature":"Impish","ivs":{"hp":15,"attack":16,"defense":15,"special_attack":17,"special_defense":11,"speed":12},"evs":{"hp":0,"attack":0,"defense":0,"special_attack":0,"special_defense":0,"speed":0},"moves":[165],"exp":428,"id":129,"pass":"SbnKZBWl","cpass":"CpW3KFHg","symbol":"","ability":"rattled"},{"name":"nincada","nature":"Impish","ivs":{"hp":19,"attack":23,"defense":16,"special_attack":28,"special_defense":25,"speed":18},"evs":{"hp":0,"attack":0,"defense":0,"special_attack":0,"special_defense":0,"speed":0},"moves":[10,206],"exp":4719,"id":290,"pass":"hY379KDi","cpass":"OxzX4anl","symbol":"","ability":"run-away"},{"name":"lotad","nature":"Gentle","ivs":{"hp":14,"attack":16,"defense":23,"special_attack":23,"special_defense":22,"speed":24},"evs":{"hp":0,"attack":0,"defense":0,"special_attack":0,"special_defense":0,"speed":0},"moves":[310,71,55],"exp":236,"id":270,"pass":"fq1TR47G","cpass":"ITj71Rrl","symbol":"","ability":"rain-dish"},{"name":"froakie","nature":"Calm","ivs":{"hp":5,"attack":9,"defense":14,"special_attack":14,"special_defense":10,"speed":4},"evs":{"hp":0,"attack":0,"defense":0,"special_attack":0,"special_defense":0,"speed":0},"moves":[1,145],"exp":314,"id":656,"pass":"EFJNYPrx","cpass":"ROfSIT8P","symbol":"","ability":"torrent"},{"name":"golett","nature":"Quirky","ivs":{"hp":11,"attack":14,"defense":14,"special_attack":11,"special_defense":15,"speed":15},"evs":{"hp":0,"attack":0,"defense":0,"special_attack":0,"special_defense":0,"speed":0},"moves":[189,310,1,325],"exp":5832,"id":622,"pass":"ssmZibg9","cpass":"ndLseJP7","symbol":"","ability":"no-guard"},{"name":"impidimp","nature":"Impish","ivs":{"hp":21,"attack":23,"defense":24,"special_attack":22,"special_defense":22,"speed":13},"evs":{"hp":0,"attack":0,"defense":0,"special_attack":0,"special_defense":0,"speed":0},"moves":[252,44,372,389],"exp":24389,"id":859,"pass":"VPVfappL","cpass":"daShoGsA","symbol":"","ability":"pickpocket"},{"name":"magikarp","nature":"Quirky","ivs":{"hp":12,"attack":13,"defense":16,"special_attack":13,"special_defense":19,"speed":16},"evs":{"hp":0,"attack":0,"defense":0,"special_attack":0,"special_defense":0,"speed":0},"moves":[165,33],"exp":7290,"id":129,"pass":"lqTjcuih","cpass":"X0EEI1Yd","symbol":"","ability":"rattled"},{"name":"slakoth","nature":"Hasty","ivs":{"hp":20,"attack":17,"defense":15,"special_attack":16,"special_defense":16,"speed":13},"evs":{"hp":0,"attack":0,"defense":0,"special_attack":0,"special_defense":0,"speed":0},"moves":[10],"exp":1250,"id":287,"pass":"AMYuRIae","cpass":"UaSBIoms","symbol":"","ability":"truant"},{"name":"slakoth","nature":"Serious","ivs":{"hp":0,"attack":4,"defense":8,"special_attack":4,"special_defense":5,"speed":7},"evs":{"hp":0,"attack":0,"defense":0,"special_attack":0,"special_defense":0,"speed":0},"moves":[10],"exp":270,"id":287,"pass":"7tVp3h2f","cpass":"UWNNiLb0","symbol":"","ability":"truant"},{"name":"impidimp","nature":"Calm","ivs":{"hp":17,"attack":17,"defense":13,"special_attack":15,"special_defense":17,"speed":11},"evs":{"hp":0,"attack":0,"defense":0,"special_attack":0,"special_defense":0,"speed":0},"moves":[252,44],"exp":216,"id":859,"pass":"mbUsYhrU","cpass":"DCWgXxx7","symbol":"","ability":"pickpocket"},{"name":"mareep","nature":"Quirky","ivs":{"hp":11,"attack":10,"defense":17,"special_attack":9,"special_defense":17,"speed":22},"evs":{"hp":0,"attack":0,"defense":0,"special_attack":0,"special_defense":0,"speed":0},"moves":[33,84],"exp":1612,"id":179,"pass":"yleDYiXU","cpass":"uo9oBh07","symbol":"","ability":"static"},{"name":"shelmet","nature":"Lonely","ivs":{"hp":16,"attack":12,"defense":14,"special_attack":19,"special_defense":18,"speed":12},"evs":{"hp":0,"attack":0,"defense":0,"special_attack":0,"special_defense":0,"speed":0},"moves":[71,51],"exp":125,"id":616,"pass":"aBgB1SOV","cpass":"okMoae1l","symbol":"","ability":"hydration"},{"name":"yamper","nature":"Adamant","ivs":{"hp":11,"attack":15,"defense":9,"special_attack":15,"special_defense":11,"speed":21},"evs":{"hp":0,"attack":0,"defense":0,"special_attack":0,"special_defense":0,"speed":0},"moves":[33,609,44],"exp":2700,"id":835,"pass":"o7cJrZJC","cpass":"omwU5ML8","symbol":"","ability":"rattled"},{"name":"gurdurr","nature":"Sassy","ivs":{"hp":17,"attack":16,"defense":11,"special_attack":16,"special_defense":16,"speed":19},"evs":{"hp":0,"attack":0,"defense":0,"special_attack":0,"special_defense":0,"speed":0},"moves":[1,88,157,21],"exp":40007,"id":533,"pass":"jQu47HkU","cpass":"AeJ8aejw","symbol":"","ability":"sheer-force"},{"name":"chewtle","nature":"Gentle","ivs":{"hp":14,"attack":16,"defense":14,"special_attack":22,"special_defense":25,"speed":23},"evs":{"hp":0,"attack":0,"defense":0,"special_attack":0,"special_defense":0,"speed":0},"moves":[33,55,44],"exp":9261,"id":833,"pass":"YLjhGwoV","cpass":"W6YZnz9Q","symbol":"","ability":"shell-armor"},{"name":"slakoth","nature":"Calm","ivs":{"hp":16,"attack":17,"defense":17,"special_attack":11,"special_defense":13,"speed":17},"evs":{"hp":0,"attack":0,"defense":0,"special_attack":0,"special_defense":0,"speed":0},"moves":[10,185],"exp":6141,"id":287,"pass":"KyIxabfa","cpass":"dBglV4bp","symbol":"","ability":"truant"},{"name":"bouffalant","nature":"Adamant","ivs":{"hp":7,"attack":18,"defense":16,"special_attack":9,"special_defense":25,"speed":13},"evs":{"hp":0,"attack":0,"defense":0,"special_attack":0,"special_defense":0,"speed":0},"moves":[33,31,279],"exp":4913,"id":626,"pass":"5rUA6Ta0","cpass":"7UoGXMls","symbol":"","ability":"soundproof"},{"name":"aegislash-shield","nature":"Gentle","ivs":{"hp":12,"attack":11,"defense":9,"special_attack":13,"special_defense":13,"speed":11},"evs":{"hp":0,"attack":0,"defense":0,"special_attack":0,"special_defense":0,"speed":0},"moves":[442,457,514,533],"exp":3375,"id":681,"pass":"DfwHUYiH","cpass":"wow9XaNu","symbol":"","ability":"stance-change"},{"name":"scraggy","nature":"Gentle","ivs":{"hp":15,"attack":13,"defense":11,"special_attack":14,"special_defense":21,"speed":18},"evs":{"hp":0,"attack":0,"defense":0,"special_attack":0,"special_defense":0,"speed":0},"moves":[371,29],"exp":729,"id":559,"pass":"s3u0NDwZ","cpass":"rAJXV7Mc","symbol":"","ability":"moxie"},{"name":"chewtle","nature":"Jolly","ivs":{"hp":16,"attack":9,"defense":17,"special_attack":18,"special_defense":11,"speed":16},"evs":{"hp":0,"attack":0,"defense":0,"special_attack":0,"special_defense":0,"speed":0},"moves":[33,55,44],"exp":4096,"id":833,"pass":"aSdhH41m","cpass":"VV60W6z9","symbol":"","ability":"strong-jaw"},{"name":"flabebe-orange","nature":"Careful","ivs":{"hp":12,"attack":15,"defense":13,"special_attack":19,"special_defense":13,"speed":12},"evs":{"hp":0,"attack":0,"defense":0,"special_attack":0,"special_defense":0,"speed":0},"moves":[22,33,584],"exp":3041,"id":669,"pass":"IKxapMgD","cpass":"vZDzefX7","symbol":"","ability":"symbiosis"},{"name":"karrablast","nature":"Hasty","ivs":{"hp":25,"attack":12,"defense":20,"special_attack":21,"special_defense":25,"speed":20},"evs":{"hp":0,"attack":0,"defense":0,"special_attack":0,"special_defense":0,"speed":0},"moves":[64,210,206],"exp":4096,"id":588,"pass":"TJj8ytkP","cpass":"tomIWkgO","symbol":"","ability":"swarm"},{"name":"floette-orange","nature":"Quiet","ivs":{"hp":12,"attack":13,"defense":15,"special_attack":13,"special_defense":18,"speed":21},"evs":{"hp":0,"attack":0,"defense":0,"special_attack":0,"special_defense":0,"speed":0},"moves":[584,75,345,572],"exp":68041,"id":670,"pass":"ii5n4XXd","cpass":"rNVOl03G","symbol":"","ability":"symbiosis"},{"name":"groudon","nature":"Careful","ivs":{"hp":27,"attack":19,"defense":20,"special_attack":16,"special_defense":20,"speed":20},"evs":{"hp":210,"attack":149,"defense":0,"special_attack":0,"special_defense":150,"speed":0},"moves":[284,619,89,359],"exp":1250000,"id":383,"pass":"WcN8IaK3","cpass":"RsjJIFnq","symbol":"","ability":"drought"},{"name":"darumaka","nature":"Rash","ivs":{"hp":12,"attack":13,"defense":16,"special_attack":16,"special_defense":22,"speed":25},"evs":{"hp":0,"attack":0,"defense":0,"special_attack":0,"special_defense":0,"speed":0},"moves":[510,424,29,7],"exp":24294,"id":554,"pass":"QyyxD0ga","cpass":"IYrPQeK5","symbol":"","ability":"hustle"},{"name":"dialga","nature":"Calm","ivs":{"special_attack":18,"defense":23,"hp":13,"speed":24,"attack":19,"special_defense":20},"evs":{"hp":0,"attack":2,"defense":0,"special_attack":143,"special_defense":81,"speed":0},"moves":[430,337,396,408],"exp":372842,"id":483,"pass":"NSSzylIq","symbol":"","ability":"telepathy"},{"name":"cramorant-gorging","nature":"Serious","ivs":{"hp":17,"attack":14,"defense":22,"special_attack":13,"special_defense":14,"speed":16},"evs":{"hp":0,"attack":0,"defense":0,"special_attack":0,"special_defense":0,"speed":0},"moves":[64,562,55,31],"exp":6859,"id":845,"pass":"fkE4GyI7","cpass":"qbVDgJNQ","symbol":"","ability":"gulp-missile"},{"name":"flabebe-orange","nature":"Rash","ivs":{"hp":15,"attack":17,"defense":16,"special_attack":16,"special_defense":8,"speed":12},"evs":{"hp":0,"attack":0,"defense":0,"special_attack":0,"special_defense":0,"speed":0},"moves":[22,33,584],"exp":2369,"id":669,"pass":"Udt9f1KS","cpass":"GXl6v8Td","symbol":"","ability":"symbiosis"},{"name":"ceruledge","nature":"Relaxed","ivs":{"hp":10,"attack":17,"defense":12,"special_attack":15,"special_defense":14,"speed":17},"evs":{"hp":0,"attack":0,"defense":0,"special_attack":0,"special_defense":0,"speed":0},"moves":[83,488,510,436],"exp":99383,"id":937,"pass":"BQgXCfag","cpass":"H6rVdP6R","symbol":"","ability":"flash-fire"},{"name":"iron-moth","nature":"Quirky","ivs":{"hp":20,"attack":17,"defense":18,"special_attack":21,"special_defense":26,"speed":20},"evs":{"hp":0,"attack":0,"defense":0,"special_attack":0,"special_defense":0,"speed":0},"moves":[36,679,435,482],"exp":175760,"id":994,"pass":"FYkyw6Lf","cpass":"V3uQXbli","symbol":"","ability":"quark-drive"},{"name":"yveltal","nature":"Mild","ivs":{"hp":12,"attack":23,"defense":19,"special_attack":18,"special_defense":9,"speed":16},"evs":{"hp":0,"attack":0,"defense":0,"special_attack":0,"special_defense":0,"speed":0},"moves":[16,555,389,403],"exp":63316,"id":717,"pass":"gRcrkGdN","cpass":"8pWM9VlX","symbol":"","ability":"dark-aura"},{"name":"yveltal","nature":"Adamant","ivs":{"hp":23,"attack":21,"defense":14,"special_attack":18,"special_defense":26,"speed":16},"evs":{"hp":0,"attack":0,"defense":0,"special_attack":0,"special_defense":0,"speed":0},"moves":[399,94,613,566],"exp":256723,"id":717,"pass":"X6HzpLfa","cpass":"Np3X7gfs","symbol":"","ability":"dark-aura"},{"name":"yveltal","nature":"Modest","ivs":{"hp":27,"attack":27,"defense":20,"special_attack":21,"special_defense":16,"speed":12},"evs":{"hp":0,"attack":0,"defense":0,"special_attack":0,"special_defense":0,"speed":0},"moves":[555,389,403,399],"exp":99383,"id":717,"pass":"R2axBmba","cpass":"w90aCnmM","symbol":"","ability":"dark-aura"},{"name":"yveltal","nature":"Lax","ivs":{"hp":18,"attack":16,"defense":21,"special_attack":22,"special_defense":26,"speed":17},"evs":{"hp":0,"attack":0,"defense":0,"special_attack":0,"special_defense":0,"speed":0},"moves":[389,403,399,94],"exp":156250,"id":717,"pass":"7GbDZ2SH","cpass":"l3FglyVd","symbol":"","ability":"dark-aura"},{"name":"zygarde-50","nature":"Gentle","ivs":{"hp":18,"attack":27,"defense":24,"special_attack":21,"special_defense":30,"speed":18},"evs":{"hp":72,"attack":120,"defense":0,"special_attack":0,"special_defense":252,"speed":1},"moves":[91,242,406,89],"exp":667085,"id":718,"pass":"huYtBHhH","cpass":"QKMTMkYx","symbol":"","ability":"power-construct"},{"name":"raboot","nature":"Mild","ivs":{"hp":16,"attack":16,"defense":11,"special_attack":14,"special_defense":14,"speed":16},"evs":{"hp":0,"attack":0,"defense":0,"special_attack":0,"special_defense":0,"speed":0},"moves":[52,98,24,488],"exp":11735,"id":814,"pass":"OLKmAzjz","cpass":"L4yUzLSd","symbol":"","ability":"libero"},{"name":"impidimp","nature":"Naive","ivs":{"hp":12,"attack":18,"defense":17,"special_attack":23,"special_defense":14,"speed":20},"evs":{"hp":0,"attack":0,"defense":0,"special_attack":0,"special_defense":0,"speed":0},"moves":[252,44,372],"exp":4913,"id":859,"pass":"xfjpJjcq","cpass":"vWrEfJ2I","symbol":"","ability":"pickpocket"},{"name":"flabebe-blue","nature":"Lonely","ivs":{"hp":16,"attack":18,"defense":14,"special_attack":16,"special_defense":16,"speed":18},"evs":{"hp":0,"attack":0,"defense":0,"special_attack":0,"special_defense":0,"speed":0},"moves":[22,33,584],"exp":2369,"id":669,"pass":"ReWFgEqc","cpass":"xLYnk7Xa","symbol":"","ability":"symbiosis"},{"name":"litten","nature":"Jolly","ivs":{"hp":16,"attack":18,"defense":13,"special_attack":17,"special_defense":15,"speed":21},"evs":{"hp":0,"attack":0,"defense":0,"special_attack":0,"special_defense":0,"speed":0},"moves":[10,52,122,154],"exp":2035,"id":725,"pass":"DIpVRdbh","cpass":"zxTUU1dl","symbol":"","ability":"blaze"},{"name":"kyurem-black","nature":"Hasty","ivs":{"hp":11,"attack":21,"defense":16,"special_attack":15,"special_defense":15,"speed":13},"evs":{"hp":0,"attack":0,"defense":0,"special_attack":0,"special_defense":0,"speed":0},"moves":[573,163,406,58],"exp":58320,"id":646,"pass":"N8NmMLCI","cpass":"mibBFl44","symbol":"","ability":"teravolt"},{"name":"frillish","nature":"Brave","ivs":{"hp":19,"attack":18,"defense":22,"special_attack":9,"special_defense":11,"speed":16},"evs":{"hp":0,"attack":0,"defense":0,"special_attack":0,"special_defense":0,"speed":0},"moves":[55,71,40,352],"exp":4096,"id":592,"pass":"kL6IPlKa","cpass":"epsUAKE0","symbol":""},{"name":"torracat","nature":"Relaxed","ivs":{"hp":12,"attack":16,"defense":13,"special_attack":11,"special_defense":17,"speed":15},"evs":{"hp":0,"attack":0,"defense":0,"special_attack":0,"special_defense":0,"speed":0},"moves":[52,122,154,44],"exp":4575,"id":726,"pass":"gOAjf5tb","cpass":"WGvTUPXa","symbol":"","ability":"blaze"},{"name":"vulpix-alola","nature":"Adamant","ivs":{"hp":15,"attack":23,"defense":15,"special_attack":22,"special_defense":11,"speed":15},"evs":{"hp":0,"attack":0,"defense":0,"special_attack":0,"special_defense":0,"speed":0},"moves":[181],"exp":216,"id":37,"pass":"YGBBXJWm","cpass":"T0sdFrPH","symbol":"","ability":"snow-cloak"},{"name":"frillish","nature":"Naughty","ivs":{"hp":10,"attack":19,"defense":20,"special_attack":14,"special_defense":20,"speed":11},"evs":{"hp":0,"attack":0,"defense":0,"special_attack":0,"special_defense":0,"speed":0},"moves":[55,71,40],"exp":216,"id":592,"pass":"c83CtCiA","cpass":"f6FHXI9N","symbol":""},{"name":"mienfoo","nature":"Adamant","ivs":{"hp":16,"attack":25,"defense":18,"special_attack":27,"special_defense":10,"speed":20},"evs":{"hp":0,"attack":0,"defense":0,"special_attack":0,"special_defense":0,"speed":0},"moves":[154,395,369,409],"exp":66505,"id":619,"pass":"yhcPQJ1f","cpass":"ekIUYWJ6","symbol":"","ability":"inner-focus"},{"name":"flabebe-yellow","nature":"Serious","ivs":{"hp":18,"attack":20,"defense":19,"special_attack":15,"special_defense":16,"speed":13},"evs":{"hp":0,"attack":0,"defense":0,"special_attack":0,"special_defense":0,"speed":0},"moves":[22,33,584],"exp":3822,"id":669,"pass":"5KEU0Kdq","cpass":"HwNs6C9s","symbol":"","ability":"symbiosis"},{"name":"flabebe-yellow","nature":"Jolly","ivs":{"hp":14,"attack":11,"defense":13,"special_attack":23,"special_defense":15,"speed":23},"evs":{"hp":0,"attack":0,"defense":0,"special_attack":0,"special_defense":0,"speed":0},"moves":[22,33],"exp":237,"id":669,"pass":"VDXWLSpd","cpass":"inyac6Du","symbol":"","ability":"flower-veil"},{"name":"rockruff","nature":"Mild","ivs":{"hp":18,"attack":22,"defense":22,"special_attack":17,"special_defense":12,"speed":10},"evs":{"hp":0,"attack":0,"defense":0,"special_attack":0,"special_defense":0,"speed":0},"moves":[33,88],"exp":3375,"id":744,"pass":"FQkU2FhO","cpass":"njvS44p0","symbol":"","ability":"keen-eye"},{"name":"vulpix-alola","nature":"Timid","ivs":{"hp":18,"attack":7,"defense":14,"special_attack":14,"special_defense":14,"speed":16},"evs":{"hp":0,"attack":0,"defense":0,"special_attack":0,"special_defense":0,"speed":0},"moves":[181,420],"exp":2197,"id":37,"pass":"PIMhSgw4","cpass":"px3oqMbq","symbol":"","ability":"snow-warning"},{"name":"mudbray","nature":"Quirky","ivs":{"hp":13,"attack":11,"defense":11,"special_attack":14,"special_defense":17,"speed":15},"evs":{"hp":0,"attack":0,"defense":0,"special_attack":0,"special_defense":0,"speed":0},"moves":[189,249],"exp":216,"id":749,"pass":"csbuG2tb","cpass":"ziJangro","symbol":"","ability":"own-tempo"},{"name":"jangmo-o","nature":"Quiet","ivs":{"hp":12,"attack":14,"defense":11,"special_attack":18,"special_defense":17,"speed":26},"evs":{"hp":0,"attack":0,"defense":0,"special_attack":0,"special_defense":0,"speed":0},"moves":[33,525,29,337],"exp":49130,"id":782,"pass":"gNs96CPo","cpass":"KcPa2uv9","symbol":"","ability":"bulletproof"},{"name":"mareep","nature":"Relaxed","ivs":{"hp":22,"attack":15,"defense":20,"special_attack":16,"special_defense":16,"speed":15},"evs":{"hp":0,"attack":0,"defense":0,"special_attack":0,"special_defense":0,"speed":0},"moves":[33,84],"exp":560,"id":179,"pass":"T8ATWztO","cpass":"0rjxSo96","symbol":"","ability":"plus"},{"name":"vulpix-alola","nature":"Mild","ivs":{"hp":20,"attack":16,"defense":22,"special_attack":17,"special_defense":14,"speed":18},"evs":{"hp":0,"attack":0,"defense":0,"special_attack":0,"special_defense":0,"speed":0},"moves":[181],"exp":343,"id":37,"pass":"rQm2TNQg","cpass":"ZbLAwmvH","symbol":"","ability":"snow-warning"},{"name":"mudbray","nature":"Bold","ivs":{"hp":19,"attack":17,"defense":18,"special_attack":15,"special_defense":15,"speed":10},"evs":{"hp":0,"attack":0,"defense":0,"special_attack":0,"special_defense":0,"speed":0},"moves":[189,249],"exp":216,"id":749,"pass":"8gDz60BE","cpass":"34bBF2cT","symbol":"","ability":"own-tempo"},{"name":"buneary","nature":"Quiet","ivs":{"hp":19,"attack":14,"defense":21,"special_attack":21,"special_defense":12,"speed":17},"evs":{"hp":0,"attack":0,"defense":0,"special_attack":0,"special_defense":0,"speed":0},"moves":[1],"exp":1331,"id":427,"pass":"hTre7ywI","cpass":"RcIrbXr5","symbol":"","ability":"limber"},{"name":"fletchling","nature":"Mild","ivs":{"hp":19,"attack":17,"defense":11,"special_attack":18,"special_defense":15,"speed":29},"evs":{"hp":0,"attack":0,"defense":0,"special_attack":0,"special_defense":0,"speed":0},"moves":[64,98],"exp":419,"id":661,"pass":"g7qbZBc4","cpass":"igdld166","symbol":"","ability":"gale-wings"},{"name":"fletchling","nature":"Hasty","ivs":{"hp":16,"attack":16,"defense":25,"special_attack":21,"special_defense":20,"speed":15},"evs":{"hp":0,"attack":0,"defense":0,"special_attack":0,"special_defense":0,"speed":0},"moves":[64,98,52],"exp":1261,"id":661,"pass":"9D8QhCNp","cpass":"d2tQw6Cl","symbol":"","ability":"big-pecks"},{"name":"vulpix-alola","nature":"Naive","ivs":{"hp":16,"attack":10,"defense":14,"special_attack":14,"special_defense":18,"speed":12},"evs":{"hp":0,"attack":0,"defense":0,"special_attack":0,"special_defense":0,"speed":0},"moves":[181],"exp":343,"id":37,"pass":"DvS4Fxwj","cpass":"LR164jdt","symbol":"","ability":"snow-cloak"},{"name":"frillish","nature":"Mild","ivs":{"hp":13,"attack":16,"defense":12,"special_attack":13,"special_defense":14,"speed":18},"evs":{"hp":0,"attack":0,"defense":0,"special_attack":0,"special_defense":0,"speed":0},"moves":[352,506,362,247],"exp":39304,"id":592,"pass":"6jlfOT7M","cpass":"qJkPP6fv","symbol":""},{"name":"rockruff","nature":"Quirky","ivs":{"hp":17,"attack":13,"defense":14,"special_attack":14,"special_defense":13,"speed":17},"evs":{"hp":0,"attack":0,"defense":0,"special_attack":0,"special_defense":0,"speed":0},"moves":[33,88],"exp":5832,"id":744,"pass":"WYiKhNG5","cpass":"hule3aZp","symbol":"","ability":"steadfast"},{"name":"scraggy","nature":"Quirky","ivs":{"hp":14,"attack":20,"defense":26,"special_attack":18,"special_defense":9,"speed":22},"evs":{"hp":0,"attack":0,"defense":0,"special_attack":0,"special_defense":0,"speed":0},"moves":[371,29],"exp":2744,"id":559,"pass":"Q2w5EBcv","cpass":"mOe4zBX1","symbol":"","ability":"intimidate"},{"name":"mienfoo","nature":"Lax","ivs":{"hp":12,"attack":22,"defense":20,"special_attack":9,"special_defense":15,"speed":12},"evs":{"hp":0,"attack":0,"defense":0,"special_attack":0,"special_defense":0,"speed":0},"moves":[1,252,154],"exp":6458,"id":619,"pass":"hn8exoM3","cpass":"cRVTS0l7","symbol":"","ability":"reckless"},{"name":"mareep","nature":"Rash","ivs":{"hp":19,"attack":7,"defense":18,"special_attack":18,"special_defense":13,"speed":18},"evs":{"hp":0,"attack":0,"defense":0,"special_attack":0,"special_defense":0,"speed":0},"moves":[33,84],"exp":742,"id":179,"pass":"r6zxaYHg","cpass":"JB5k2kNa","symbol":"","ability":"static"},{"name":"vulpix-alola","nature":"Timid","ivs":{"hp":12,"attack":16,"defense":15,"special_attack":18,"special_defense":17,"speed":7},"evs":{"hp":0,"attack":0,"defense":0,"special_attack":0,"special_defense":0,"speed":0},"moves":[181,420,196],"exp":4913,"id":37,"pass":"QsRd6dWz","cpass":"MvOBf3zW","symbol":"","ability":"snow-cloak"},{"name":"slakoth","nature":"Modest","ivs":{"hp":9,"attack":21,"defense":17,"special_attack":15,"special_defense":20,"speed":16},"evs":{"hp":0,"attack":0,"defense":0,"special_attack":0,"special_defense":0,"speed":0},"moves":[10],"exp":1663,"id":287,"pass":"Hjncon7f","cpass":"JjFOEvqu","symbol":"","ability":"truant"},{"name":"golett","nature":"Lax","ivs":{"hp":10,"attack":12,"defense":15,"special_attack":12,"special_defense":19,"speed":12},"evs":{"hp":0,"attack":0,"defense":0,"special_attack":0,"special_defense":0,"speed":0},"moves":[189,310,1],"exp":1000,"id":622,"pass":"lUOfQ1Zf","cpass":"LiazaYXb","symbol":"","ability":"iron-fist"},{"name":"kyurem-black","nature":"Serious","ivs":{"hp":14,"attack":11,"defense":21,"special_attack":23,"special_defense":17,"speed":16},"evs":{"hp":0,"attack":0,"defense":0,"special_attack":0,"special_defense":0,"speed":0},"moves":[58,304,559,59],"exp":243890,"id":646,"pass":"N7ux9aT9","cpass":"WhCgVOjh","symbol":"","ability":"teravolt"},{"name":"bouffalant","nature":"Serious","ivs":{"hp":18,"attack":19,"defense":13,"special_attack":14,"special_defense":27,"speed":17},"evs":{"hp":0,"attack":0,"defense":0,"special_attack":0,"special_defense":0,"speed":0},"moves":[33,31],"exp":3375,"id":626,"pass":"hVtZ19JO","cpass":"FKCKy4U0","symbol":"✨","ability":"reckless"},{"name":"regieleki","nature":"Modest","ivs":{"hp":21,"attack":21,"defense":20,"special_attack":20,"special_defense":17,"speed":17},"evs":{"hp":0,"attack":0,"defense":0,"special_attack":0,"special_defense":0,"speed":0},"moves":[245,819,85,37],"exp":231491,"id":894,"pass":"GsxHsDDB","cpass":"LyNecdu3","symbol":"","ability":"transistor"},{"name":"charmander","nature":"Gentle","ivs":{"hp":10,"attack":8,"defense":13,"special_attack":22,"special_defense":14,"speed":18},"evs":{"hp":0,"attack":0,"defense":0,"special_attack":0,"special_defense":0,"speed":0},"moves":[10,52],"exp":419,"id":4,"pass":"TpbpWVfs","cpass":"vEUce5Z2","symbol":"","ability":"solar-power"},{"name":"squirtle","nature":"Naive","ivs":{"hp":15,"attack":18,"defense":15,"special_attack":12,"special_defense":15,"speed":19},"evs":{"hp":0,"attack":0,"defense":0,"special_attack":0,"special_defense":0,"speed":0},"moves":[33,55],"exp":314,"id":7,"pass":"DfwgXoe2","cpass":"FguiQX2B","symbol":"","ability":"torrent"},{"name":"abra","nature":"Adamant","ivs":{"hp":18,"attack":18,"defense":12,"special_attack":9,"special_defense":20,"speed":12},"evs":{"hp":0,"attack":0,"defense":0,"special_attack":0,"special_defense":0,"speed":0},"moves":[165],"exp":2035,"id":63,"pass":"aCinjCq7","cpass":"zDlXgrzi","symbol":"","ability":"synchronize"},{"name":"magikarp","nature":"Hasty","ivs":{"hp":10,"attack":11,"defense":11,"special_attack":10,"special_defense":13,"speed":13},"evs":{"hp":0,"attack":0,"defense":0,"special_attack":0,"special_defense":0,"speed":0},"moves":[165,33],"exp":7290,"id":129,"pass":"kvgeJJGp","cpass":"hZ0EiO9k","symbol":"","ability":"rattled"},{"name":"charmeleon","nature":"Serious","ivs":{"hp":20,"attack":15,"defense":20,"special_attack":15,"special_defense":14,"speed":13},"evs":{"hp":0,"attack":0,"defense":0,"special_attack":0,"special_defense":0,"speed":0},"moves":[52,225,424,163],"exp":13411,"id":5,"pass":"KLSNQw7z","cpass":"BN9csN6P","symbol":"","ability":"solar-power"},{"name":"magikarp","nature":"Serious","ivs":{"hp":23,"attack":16,"defense":21,"special_attack":19,"special_defense":19,"speed":18},"evs":{"hp":0,"attack":0,"defense":0,"special_attack":0,"special_defense":0,"speed":0},"moves":[165,33],"exp":6141,"id":129,"pass":"F1BaZTYy","cpass":"oJNUM1DB","symbol":"","ability":"rattled"},{"name":"charmeleon","nature":"Jolly","ivs":{"hp":20,"attack":8,"defense":27,"special_attack":17,"special_defense":9,"speed":9},"evs":{"hp":0,"attack":0,"defense":0,"special_attack":0,"special_defense":0,"speed":0},"moves":[10,52,225,424],"exp":8825,"id":5,"pass":"Mnf5iQKR","cpass":"3cVsHmiv","symbol":"","ability":"blaze"},{"name":"kangaskhan","nature":"Sassy","ivs":{"hp":13,"attack":10,"defense":22,"special_attack":24,"special_defense":13,"speed":16},"evs":{"hp":0,"attack":0,"defense":0,"special_attack":0,"special_defense":0,"speed":0},"moves":[1,252],"exp":1331,"id":115,"pass":"yyMSoGz7","cpass":"QfDviT5S","symbol":"","ability":"scrappy"},{"name":"aerodactyl","nature":"Naive","ivs":{"hp":10,"attack":12,"defense":18,"special_attack":11,"special_defense":14,"speed":19},"evs":{"hp":0,"attack":0,"defense":0,"special_attack":0,"special_defense":0,"speed":0},"moves":[44,246,17],"exp":7290,"id":142,"pass":"wnBoFX6A","cpass":"LqJesnc8","symbol":"","ability":"unnerve"},{"name":"abra","nature":"Sassy","ivs":{"hp":13,"attack":11,"defense":15,"special_attack":15,"special_defense":15,"speed":11},"evs":{"hp":0,"attack":0,"defense":0,"special_attack":0,"special_defense":0,"speed":0},"moves":[165],"exp":1261,"id":63,"pass":"LvyY7Izu","cpass":"gaC26lnU","symbol":"","ability":"inner-focus"},{"name":"charmander","nature":"Gentle","ivs":{"hp":14,"attack":16,"defense":15,"special_attack":7,"special_defense":16,"speed":14},"evs":{"hp":0,"attack":0,"defense":0,"special_attack":0,"special_defense":0,"speed":0},"moves":[10,52],"exp":560,"id":4,"pass":"OH5laAtE","cpass":"o8tAw9ZY","symbol":"","ability":"blaze"},{"name":"charmander","nature":"Sassy","ivs":{"hp":13,"attack":21,"defense":21,"special_attack":16,"special_defense":14,"speed":22},"evs":{"hp":0,"attack":0,"defense":0,"special_attack":0,"special_defense":0,"speed":0},"moves":[10,52],"exp":419,"id":4,"pass":"VPgklAk6","cpass":"WL6K7sXL","symbol":"","ability":"blaze"},{"name":"abra","nature":"Timid","ivs":{"hp":15,"attack":12,"defense":20,"special_attack":24,"special_defense":12,"speed":12},"evs":{"hp":0,"attack":0,"defense":0,"special_attack":0,"special_defense":0,"speed":0},"moves":[165],"exp":236,"id":63,"pass":"UH8Muq3i","cpass":"Hw6onRmj","symbol":"","ability":"synchronize"},{"name":"bulbasaur","nature":"Jolly","ivs":{"hp":5,"attack":8,"defense":6,"special_attack":5,"special_defense":4,"speed":1},"evs":{"hp":0,"attack":0,"defense":0,"special_attack":0,"special_defense":0,"speed":0},"moves":[33,22,75],"exp":1612,"id":1,"pass":"CLqhbLdv","cpass":"1e6paPNd","symbol":"","ability":"chlorophyll"},{"name":"magikarp","nature":"Naughty","ivs":{"hp":15,"attack":12,"defense":11,"special_attack":13,"special_defense":17,"speed":18},"evs":{"hp":0,"attack":0,"defense":0,"special_attack":0,"special_defense":0,"speed":0},"moves":[165],"exp":4218,"id":129,"pass":"IvVVioo5","cpass":"Zzne0NwF","symbol":"","ability":"swift-swim"},{"name":"charmander","nature":"Adamant","ivs":{"hp":14,"attack":12,"defense":13,"special_attack":9,"special_defense":6,"speed":13},"evs":{"hp":0,"attack":0,"defense":0,"special_attack":0,"special_defense":0,"speed":0},"moves":[10,52],"exp":742,"id":4,"pass":"YbEGONyL","cpass":"UiVrTRS8","symbol":"","ability":"blaze"},{"name":"magikarp","nature":"Hasty","ivs":{"hp":9,"attack":19,"defense":14,"special_attack":24,"special_defense":26,"speed":18},"evs":{"hp":0,"attack":0,"defense":0,"special_attack":0,"special_defense":0,"speed":0},"moves":[165],"exp":911,"id":129,"pass":"2OJuN3ez","cpass":"LICi19xO","symbol":"","ability":"swift-swim"},{"name":"hawlucha","nature":"Sassy","ivs":{"hp":9,"attack":10,"defense":16,"special_attack":1,"special_defense":10,"speed":14},"evs":{"hp":0,"attack":0,"defense":0,"special_attack":0,"special_defense":0,"speed":0},"moves":[33,17,332],"exp":4096,"id":701,"pass":"BULqRPg5","cpass":"4vjCFRaQ","symbol":"","ability":"mold-breaker"},{"name":"frillish","nature":"Jolly","ivs":{"hp":21,"attack":15,"defense":14,"special_attack":12,"special_defense":16,"speed":14},"evs":{"hp":0,"attack":0,"defense":0,"special_attack":0,"special_defense":0,"speed":0},"moves":[55,71,40],"exp":512,"id":592,"pass":"IZLxic8H","cpass":"QOip4O3q","symbol":""},{"name":"torracat","nature":"Quiet","ivs":{"hp":16,"attack":15,"defense":13,"special_attack":23,"special_defense":14,"speed":15},"evs":{"hp":0,"attack":0,"defense":0,"special_attack":0,"special_defense":0,"speed":0},"moves":[52,122,154,44],"exp":5460,"id":726,"pass":"RF5Gg52P","cpass":"I2AA6ijj","symbol":"","ability":"blaze"},{"name":"rockruff-own-tempo","nature":"Rash","ivs":{"hp":19,"attack":20,"defense":20,"special_attack":18,"special_defense":17,"speed":22},"evs":{"hp":0,"attack":0,"defense":0,"special_attack":0,"special_defense":0,"speed":0},"moves":[33,88,44,317],"exp":17576,"id":744,"pass":"ONcwFLit","cpass":"MuJTy7Td","symbol":"","ability":"own-tempo"},{"name":"mudbray","nature":"Adamant","ivs":{"hp":14,"attack":22,"defense":21,"special_attack":16,"special_defense":21,"speed":19},"evs":{"hp":0,"attack":0,"defense":0,"special_attack":0,"special_defense":0,"speed":0},"moves":[249,24,523,23],"exp":5832,"id":749,"pass":"xdjDcMNl","cpass":"72mSYGCr","symbol":"","ability":"stamina"},{"name":"golurk","nature":"Quiet","ivs":{"hp":12,"attack":17,"defense":15,"special_attack":13,"special_defense":18,"speed":14},"evs":{"hp":0,"attack":0,"defense":0,"special_attack":0,"special_defense":0,"speed":0},"moves":[707,5,247,566],"exp":110592,"id":623,"pass":"DjBBBeFZ","cpass":"wCg0vm8o","symbol":"","ability":"iron-fist"}],"inv":{"pc":24615,"region":"galar","exp":0,"avtar":"8","template":"2","id":"grey","data":"black","hometown":"Galar","team":"1","name":"&#x3164;&#x3164;&#x3164; #offline","win":75,"candy":0,"vitamin":0,"berry":0},"balls":{"regular":39,"great":-1,"ultra":0,"safari":0,"quick":0,"moon":4,"premier":1,"beast":4,"repeat":69},"extra":{"date":"25/02/2024","megas":{},"huntd":"2024-04-04","hunts":66,"saf":"unova","lastsafari":"2024-04-01","display":"level","sort":"level","referred":5884907214,"refer":[5321235871,5321235871,5006994005,833985714,1345355862,5995822853,6669536790],"hunting":true,"evhunt":0,"evh":"defense","rankRewards":{"claimedLevel":0,"lastClaimAtUtc":null},"rankLevel":1},"teams":{"1":["Zl10eLU8","BWhOdvXQ","59KGnSdJ","4Q1TWlrM","WcN8IaK3","huYtBHhH"],"2":[],"3":[],"4":["Ivjhc7o2","G4GQ22uO","M2B1wg8p","mVipByeR","Vfr9BKZa","aoVPYjyq"],"5":[],"6":["WcN8IaK3","mbUsYhrU","KPqkzxvy","rdKwAAKs","74Bct6CN","59KGnSdJ"]},"pokecaught":["scorbunny","aerodactyl","raboot","bisharp","golbat","mewtwo","salamence","blaziken","marshtomp","spiritomb","gurdurr","magmar","pupitar","gible","flabebe-yellow","rockruff","absol","kangaskhan","buneary","ralts","kirlia","pikachu-hoenn-cap","wyrdeer","abra","starly","pikachu-cosplay","riolu","wimpod","nincada","morgrem","rufflet","combusken","torchic","vigoroth","squirtle","chespin","golett","slakoth","bulbasaur","spectrier","voltorb","mankey","guzzlord","naganadel","marshadow","lycanroc-midnight","rockruff-own-tempo","magearna","solgaleo","kartana","charmander","floette-blue","frillish","happiny","wurmple","silcoon","beautifly","beautifly","dustox","chansey","greninja","pikachu-unova-cap","magikarp","nidoran-m","staryu","blissey","lugia","dialga","celebi","groudon","bellsprout","chinchou","doduo","shroomish","gardevoir","arceus-rock","lotad","froakie","impidimp","mareep","shelmet","yamper","chewtle","bouffalant","aegislash-shield","scraggy","flabebe-orange","karrablast","floette-orange","darumaka","pawniard","cramorant-gorging","giratina-altered","arceus-poison","palkia","ceruledge","iron-moth","regigigas","yveltal","zygarde-complete","flabebe-blue","litten","floette-red","torracat","vulpix-alola","mienfoo","mudbray","jangmo-o","fletchling","kyurem-black","kyurem-black","kyurem-black","kyurem-black","kyurem-white","regieleki","charmeleon","hawlucha","golurk"],"pokeseen":["scorbunny","aerodactyl","mewtwo","alakazam","psyduck","shellder","kakuna","graveler","gastly","growlithe","venonat","tangela","drowzee","kangaskhan","seel","mr-mime","oddish","omanyte","raboot","rhydon","chikorita","geodude","magikarp","goldeen","snubbull","qwilfish","swinub","wartortle","marill","gligar","pikachu-hoenn-cap","ursaring","poliwag","croconaw","cascoon","lunatone","beldum","voltorb","sealeo","bisharp","golbat","kirlia","latias","metagross","latios","swampert","deoxys-normal","registeel","salamence","metang","blaziken","marshtomp","numel","linoone","electrike","doduo","gulpin","carvanha","rhyhorn","kecleon","lairon","spiritomb","bidoof","elekid","chansey","pachirisu","togetic","mantyke","magby","snorunt","barboach","girafarig","porygon2","roselia","clefairy","onix","buizel","kricketot","dewott","pawniard","tynamo","croagunk","duosion","remoraid","lampent","slakoth","gurdurr","cottonee","solrock","gothita","tropius","magmar","pupitar","maractus","lickitung","sigilyph","jigglypuff","tepig","herdier","dunsparce","palpitoad","noibat","karrablast","poliwhirl","foongus","basculin-blue-striped","shelmet","stunfisk","spearow","vibrava","gothorita","gabite","druddigon","spinarak","ekans","spinda","basculin-red-striped","snover","heatmor","trubbish","bellsprout","ditto","teddiursa","pinsir","dedenne","steenee","cutiefly","bagon","misdreavus","pancham","alomomola","litleo","skrelp","sableye","trumbeak","phantump","sneasel","morelull","komala","rockruff","pikipek","oricorio-pau","luvdisc","dartrix","wishiwashi-school","floette-orange","rufflet","floette-eternal","oricorio-pom-pom","corphish","gible","flabebe-yellow","exeggcute","cranidos","dewpider","geodude-alola","vullaby","dragonair","trapinch","natu","emolga","mankey","stufful","absol","pyukumuku","larvitar","clauncher","fletchling","boldore","fletchinder","tauros","popplio","tirtouga","chinchou","buneary","carbink","miltank","cleffa","hakamo-o","roggenrola","pineco","primeape","zorua","klefki","minccino","nosepass","tentacool","porygon","ralts","abra","basculin-white-striped","bronzor","eevee-starter","scyther","grotle","shinx","ponyta","goomy","prinplup","wyrdeer","monferno","starly","aipom","wurmple","machop","haunter","pikachu-cosplay","vulpix","piloswine","silcoon","petilil","staravia","duskull","spheal","togepi","finneon","magneton","machoke","zubat","cherubi","qwilfish-hisui","chatot","yanma","rowlet","growlithe-hisui","basculegion-female","magnemite","bergmite","bonsly","munchlax","unown-exclamation","carnivine","chimchar","riolu","voltorb-hisui","piplup","joltik","cramorant-gorging","skwovet","lapras","gossifleur","yamper","pumpkaboo-average","morgrem","wishiwashi-solo","budew","gourgeist-large","nickit","tyrogue","indeedee-male","mr-mime-galar","sliggoo","wimpod","spritzee","corsola-galar","clobbopus","hattrem","durant","sizzlipede","grubbin","wooper","wynaut","dottler","baltoy","drizzile","wingull","nincada","binacle","honedge","morpeko-hangry","skorupi","darmanitan-galar-standard","silicobra","dreepy","hoothoot","dwebble","cufant","rookidee","litwick","helioptile","cubchoo","nuzleaf","impidimp","chewtle","blipbug","tranquill","rolycoly","darumaka-galar","corvisquire","scraggy","falinks","toxtricity-low-key","zweilous","mudbray","ferroseed","blitzle","combusken","totodile","sandshrew","charmander","grimer","torchic","cyndaquil","sandile","rellor","thwackey","axew","mudkip","torracat","vigoroth","tauros-paldea-combat-breed","squirtle","chespin","golett","bulbasaur","regieleki","zarude","calyrex-ice","zarude-dada","spectrier","urshifu-single-strike","glastrier","charjabug","sobble","inkay","meowstic-female","swirlix","mareanie","torkoal","grovyle","arceus-dark","dialga","arceus-dragon","arceus-flying","palkia","zeraora","guzzlord","poipole","naganadel","silvally-rock","buzzwole","magearna","marshadow","kommo-o","lycanroc-midnight","rockruff-own-tempo","silvally-flying","nihilego","solgaleo","kartana","frillish","floette-blue","calyrex-shadow","calyrex","urshifu-rapid-strike","zekrom","kyurem-white","kyurem-black","keldeo-resolute","reshiram","happiny","swablu","dustox","houndour","beautifly","turtwig","meditite","mime-jr","shieldon","greninja","pikachu-unova-cap","nidoran-m","staryu","blissey","lugia","celebi","groudon","shroomish","nidorina","koffing","paras","electabuzz","kadabra","caterpie","gardevoir","krabby","meowth","nidoran-f","dratini","blastoise","arceus-water","regigigas","arceus-rock","steelix","leafeon","uxie","gliscor","bastiodon","tangrowth","golem","hippowdon","sudowoodo","pelipper","eevee","aron","lotad","frogadier","froakie","mareep","bouffalant","litten","mienfoo","aegislash-shield","flabebe-orange","darumaka","darmanitan-standard","arceus","arceus-psychic","arceus-electric","arceus-fairy","arceus-poison","giratina-altered","dusknoir","probopass","tentacruel","altaria","mantine","milotic","umbreon","glaceon","roserade","gengar","espeon","porygon-z","togekiss","empoleon","golduck","houndoom","magmortar","okidogi","ceruledge","wo-chien","ting-lu","chien-pao","fezandipiti","iron-moth","excadrill","sawsbuck-spring","electivire","granbull","haxorus","crabominable","eelektross","rhyperior","iron-leaves","krookodile","toucannon","braviary","kleavor","rampardos","torterra","krokorok","golurk","dodrio","malamar","sawsbuck-summer","scizor","bruxish","zangoose","rillaboom","fraxure","decidueye","sawsbuck-autumn","incineroar","hitmonlee","pignite","eelektrik","sawsbuck-winter","feraligatr","beartic","emboar","chesnaught","archaludon","sandslash","gouging-fire","slowbro","pecharunt","quilladin","skarmory","bellossom","comfey","slowking","gothitelle","araquanid","hitmontop","dewgong","hitmonchan","araquanid-totem","yveltal","hoopa-unbound","zygarde-complete","lombre","cryogonal","politoed","goodra","ludicolo","mamoswine","victreebel","honchkrow","weepinbell","arbok","conkeldurr","tyranitar","garchomp","trevenant","banette","dragonite","mightyena","ariados","escavalier","watchog","melmetal","flabebe-blue","floette-red","vulpix-alola","flabebe-red","jangmo-o","flabebe-white","gyarados","kingler","kabutops","flareon","parasect","machamp","weezing","metapod","cloyster","omastar","poliwrath","marowak","terrakion","regidrago","charmeleon","hawlucha","diancie","blacephalon","noivern"],"refers":4,"settings":{"max_poke":6,"dual_type":true,"min_6l":0,"max_6l":6,"min_level":1,"max_level":100,"switch":true,"key_item":true,"sandbox":false,"random":false,"preview":"Down","pin":false,"ban_types":[],"allow_types":[],"ban_regions":[],"allow_regions":[],"type_effects":true},"tms":{"36":1,"109":1,"122":1,"131":1}},"reset":false}]