[{"user_id":6501240419,"data":{"pokes":[{"name":"chespin","id":650,"nature":"Lax","exp":135,"pass":"jE187GKu","ivs":{"hp":3,"attack":15,"defense":27,"special_attack":11,"special_defense":4,"speed":22},"symbol":"","evs":{"hp":0,"attack":0,"defense":0,"special_attack":0,"special_defense":0,"speed":0},"moves":[22],"ability":"bulletproof"}],"inv":{"pc":5000,"region":"kanto","exp":0,"avtar":"1","template":"1","id":"grey","data":"black","hometown":"Kalos","name":"&#x1F1E7; &#x1F1F4; &#x1F1F9;","team":"1"},"balls":{"regular":10,"great":7,"ultra":3},"extra":{"date":"13/04/2024","megas":{},"rankRewards":{"claimedLevel":0,"lastClaimAtUtc":null},"rankLevel":1},"settings":{"max_poke":6,"dual_type":true,"min_6l":0,"max_6l":6,"min_level":1,"max_level":100,"switch":true,"key_item":true,"sandbox":false,"random":false,"preview":"no","pin":false,"ban_types":[],"allow_types":[],"ban_regions":[],"allow_regions":[],"type_effects":true},"pokecaught":["chespin"],"pokeseen":["chespin"],"teams":{"1":["jE187GKu"],"2":[],"3":[],"4":[],"5":[],"6":[]}},"reset":false}]