[{"user_id":7035482301,"data":{"pokes":[{"name":"crawdaunt","nature":"Quirky","ivs":{"hp":14,"attack":25,"defense":16,"special_attack":11,"special_defense":25,"speed":11},"evs":{"hp":0,"attack":7,"defense":1,"special_attack":2,"special_defense":0,"speed":0},"moves":[61,282,458,400],"exp":32851,"id":342,"pass":"3Z6liL2x","symbol":"","ability":"adaptability"},{"name":"pikachu-hoenn-cap","nature":"Rash","ivs":{"hp":17,"attack":17,"defense":22,"special_attack":20,"special_defense":13,"speed":15},"evs":{"hp":0,"attack":0,"defense":0,"special_attack":0,"special_defense":0,"speed":0},"moves":[98,609,364,209],"exp":19683,"id":25,"pass":"s794H4qE","cpass":"dVgUrTMh","symbol":"","nickname":"Pikachu Spe","ability":"static"},{"name":"dragonite","nature":"Quirky","ivs":{"hp":17,"attack":14,"defense":11,"special_attack":17,"special_defense":14,"speed":8},"evs":{"hp":85,"attack":106,"defense":86,"special_attack":89,"special_defense":29,"speed":114},"moves":[21,401,407,200],"exp":362604,"id":149,"pass":"JjvunLNd","cpass":"9zAy6AlX","symbol":"","ability":"inner-focus"},{"name":"magnemite","nature":"Adamant","ivs":{"hp":15,"attack":17,"defense":20,"special_attack":19,"special_defense":18,"speed":12},"evs":{"hp":0,"attack":2,"defense":0,"special_attack":0,"special_defense":0,"speed":2},"moves":[33,84,209],"exp":13375,"id":81,"pass":"Ku4VcUtO","cpass":"DrQEdSuH","symbol":"","ability":"sturdy"},{"name":"electabuzz","nature":"Bold","ivs":{"hp":12,"attack":11,"defense":16,"special_attack":13,"special_defense":13,"speed":15},"evs":{"hp":0,"attack":0,"defense":0,"special_attack":0,"special_defense":0,"speed":0},"moves":[129,351,9,435],"exp":85184,"id":125,"pass":"gl0Orc7V","cpass":"iPoGJ73Y","symbol":"","ability":"static"},{"name":"weepinbell","nature":"Naive","ivs":{"hp":15,"attack":23,"defense":20,"special_attack":16,"special_defense":12,"speed":13},"evs":{"hp":0,"attack":0,"defense":0,"special_attack":0,"special_defense":0,"speed":0},"moves":[35,35,51,282],"exp":47846,"id":70,"pass":"TDWaZUCL","cpass":"hiD5zRmI","symbol":"","ability":"gluttony"},{"name":"basculegion-female","nature":"Bold","ivs":{"hp":19,"attack":22,"defense":20,"special_attack":13,"special_defense":16,"speed":20},"evs":{"hp":1,"attack":0,"defense":0,"special_attack":0,"special_defense":0,"speed":0},"moves":[453,44,29,242],"exp":39547,"id":902,"pass":"X8oAXbGw","cpass":"E2ronbAF","symbol":"","ability":"adaptability"},{"name":"dialga","nature":"Lonely","ivs":{"hp":19,"attack":23,"defense":21,"special_attack":23,"special_defense":26,"speed":17},"evs":{"hp":0,"attack":0,"defense":0,"special_attack":0,"special_defense":0,"speed":0},"moves":[430,337,396,408],"exp":283726,"id":483,"pass":"N2HjSAvz","cpass":"dOZn0fH9","symbol":"","ability":"telepathy"},{"name":"dialga","nature":"Modest","ivs":{"hp":15,"attack":20,"defense":17,"special_attack":18,"special_defense":14,"speed":21},"evs":{"hp":0,"attack":0,"defense":0,"special_attack":0,"special_defense":0,"speed":0},"moves":[430,337,396,408],"exp":327680,"id":483,"pass":"CZ6Bnqrw","cpass":"gRaQXaqn","symbol":"","ability":"pressure"},{"name":"kakuna","nature":"Lax","ivs":{"hp":22,"attack":21,"defense":22,"special_attack":20,"special_defense":21,"speed":20},"evs":{"hp":0,"attack":0,"defense":0,"special_attack":0,"special_defense":0,"speed":0},"moves":[165],"exp":512,"id":14,"pass":"2rESs2GM","cpass":"nKl5BV1G","symbol":"","ability":"shed-skin"},{"name":"pikachu-sinnoh-cap","nature":"Calm","ivs":{"hp":19,"attack":22,"defense":13,"special_attack":18,"special_defense":18,"speed":20},"evs":{"hp":0,"attack":0,"defense":0,"special_attack":0,"special_defense":0,"speed":0},"moves":[98,609,364,209],"exp":10648,"id":25,"pass":"TW4cjnTS","cpass":"UA9TiZ5e","symbol":"","nickname":"Pikachu Spe","ability":"static"},{"name":"pikachu-cosplay","nature":"Quirky","ivs":{"hp":16,"attack":23,"defense":24,"special_attack":28,"special_defense":18,"speed":24},"evs":{"hp":0,"attack":0,"defense":0,"special_attack":0,"special_defense":0,"speed":0},"moves":[98,609,364,209],"exp":21952,"id":25,"pass":"rDnM4HBb","cpass":"EgJZHjHe","symbol":"","nickname":"Pikachu Spe","ability":"lightning-rod"},{"name":"pikachu-sinnoh-cap","nature":"Bold","ivs":{"hp":17,"attack":19,"defense":23,"special_attack":14,"special_defense":24,"speed":11},"evs":{"hp":0,"attack":0,"defense":0,"special_attack":0,"special_defense":0,"speed":0},"moves":[84,98,609,364],"exp":8000,"id":25,"pass":"p2A3zDH4","cpass":"bL0Mxmad","symbol":"","nickname":"Pikachu Spe","ability":"lightning-rod"},{"name":"delphox","nature":"Serious","ivs":{"hp":20,"attack":25,"defense":19,"special_attack":20,"special_defense":18,"speed":23},"evs":{"hp":0,"attack":0,"defense":0,"special_attack":0,"special_defense":0,"speed":0},"moves":[488,60,83,473],"exp":56660,"id":655,"pass":"QPu0MVZ6","cpass":"15eQV0Xf","symbol":"","nickname":"Delphox SpA","ability":"magician"},{"name":"pikachu-sinnoh-cap","nature":"Quiet","ivs":{"hp":29,"attack":28,"defense":18,"special_attack":20,"special_defense":23,"speed":18},"evs":{"hp":0,"attack":0,"defense":0,"special_attack":0,"special_defense":0,"speed":0},"moves":[84,98,609,364],"exp":8000,"id":25,"pass":"MoDhqctm","cpass":"ew0hvLpE","symbol":"","nickname":"Pikachu Spe","ability":"static"},{"name":"pikachu-belle","nature":"Brave","ivs":{"hp":21,"attack":27,"defense":25,"special_attack":15,"special_defense":17,"speed":21},"evs":{"hp":0,"attack":0,"defense":0,"special_attack":0,"special_defense":0,"speed":0},"moves":[84,98,609],"exp":1000,"id":25,"pass":"2wY55pnD","cpass":"UZ1Ci1TB","symbol":"","nickname":"Pikachu Spe","ability":"static"},{"name":"ditto","nature":"Bold","ivs":{"hp":18,"attack":12,"defense":12,"special_attack":18,"special_defense":18,"speed":18},"evs":{"hp":0,"attack":0,"defense":0,"special_attack":0,"special_defense":0,"speed":0},"moves":[165],"exp":512,"id":132,"pass":"Jx8Ut34N","cpass":"1SoPOXwi","symbol":"","ability":"limber"},{"name":"karrablast","nature":"Naive","ivs":{"hp":28,"attack":18,"defense":16,"special_attack":13,"special_defense":15,"speed":19},"evs":{"hp":0,"attack":0,"defense":0,"special_attack":0,"special_defense":0,"speed":0},"moves":[64,210,206],"exp":3375,"id":588,"pass":"iHHf6UyY","cpass":"PrChzhW9","symbol":"","ability":"shed-skin"},{"name":"swinub","nature":"Lax","ivs":{"hp":19,"attack":23,"defense":18,"special_attack":12,"special_defense":22,"speed":15},"evs":{"hp":0,"attack":0,"defense":0,"special_attack":0,"special_defense":0,"speed":0},"moves":[33,189,181,420],"exp":17280,"id":220,"pass":"YgESUGEw","cpass":"W57zHBkT","symbol":"","ability":"thick-fat"},{"name":"dragonite","nature":"Lonely","ivs":{"special_defense":22,"special_attack":13,"attack":26,"hp":21,"speed":20,"defense":16},"evs":{"hp":0,"attack":0,"defense":0,"special_attack":0,"special_defense":0,"speed":0},"moves":[21,401,407,200],"exp":156250,"id":149,"pass":"gegyIqcT","symbol":"","ability":"multiscale"},{"name":"gabite","nature":"Mild","ivs":{"hp":18,"attack":21,"defense":12,"special_attack":20,"special_defense":19,"speed":22},"evs":{"hp":0,"attack":0,"defense":0,"special_attack":0,"special_defense":0,"speed":0},"moves":[328,530,523,44],"exp":49130,"id":444,"pass":"o4vvpgJ9","cpass":"t1w3tUbQ","symbol":"","ability":"rough-skin"},{"name":"gabite","nature":"Mild","ivs":{"hp":18,"attack":21,"defense":12,"special_attack":20,"special_defense":19,"speed":22},"evs":{"hp":0,"attack":0,"defense":0,"special_attack":0,"special_defense":0,"speed":0},"moves":[328,530,523,44],"exp":49130,"id":444,"pass":"E1v21kkL","cpass":"t1w3tUbQ","symbol":"","ability":"sand-veil"},{"name":"absol","nature":"Naive","ivs":{"hp":9,"attack":21,"defense":12,"special_attack":17,"special_defense":22,"speed":9},"evs":{"hp":0,"attack":0,"defense":0,"special_attack":0,"special_defense":0,"speed":0},"moves":[98,282],"exp":3798,"id":359,"pass":"pOj3lYnp","cpass":"0rwL8LtY","symbol":"","ability":"super-luck"},{"name":"morgrem","nature":"Relaxed","ivs":{"hp":9,"attack":4,"defense":7,"special_attack":4,"special_defense":3,"speed":6},"evs":{"hp":0,"attack":0,"defense":0,"special_attack":0,"special_defense":0,"speed":0},"moves":[44,252,372,389],"exp":35937,"id":860,"pass":"FfSjWeAG","cpass":"CcVrlhWe","symbol":"","nickname":"SpA","ability":"prankster"},{"name":"girafarig","nature":"Quiet","ivs":{"hp":10,"attack":19,"defense":24,"special_attack":17,"special_defense":16,"speed":16},"evs":{"hp":0,"attack":0,"defense":0,"special_attack":0,"special_defense":0,"speed":0},"moves":[310,372,23,60],"exp":9261,"id":203,"pass":"5yFIYhUd","cpass":"5ctJs26L","symbol":"","nickname":"SpA","ability":"inner-focus"},{"name":"sandy-shocks","nature":"Lonely","ivs":{"hp":13,"attack":12,"defense":17,"special_attack":11,"special_defense":15,"speed":13},"evs":{"hp":0,"attack":0,"defense":0,"special_attack":0,"special_defense":0,"speed":0},"moves":[209,523,451,161],"exp":80000,"id":989,"pass":"rOtLEYPP","cpass":"q3l5sVD5","symbol":"","nickname":"SpA","ability":"protosynthesis"},{"name":"sandy-shocks","nature":"Calm","ivs":{"hp":24,"attack":11,"defense":18,"special_attack":19,"special_defense":11,"speed":18},"evs":{"hp":0,"attack":0,"defense":0,"special_attack":0,"special_defense":0,"speed":0},"moves":[209,523,451,161],"exp":80000,"id":989,"pass":"28ExElzR","cpass":"70vSY725","symbol":"","nickname":"SpA","ability":"protosynthesis"},{"name":"sandy-shocks","nature":"Mild","ivs":{"hp":12,"attack":27,"defense":19,"special_attack":30,"special_defense":14,"speed":18},"evs":{"hp":0,"attack":0,"defense":0,"special_attack":0,"special_defense":0,"speed":0},"moves":[209,523,451,161],"exp":80000,"id":989,"pass":"ywPYqCgM","cpass":"NBOTVMia","symbol":"","nickname":"SpA","ability":"protosynthesis"},{"name":"bisharp","nature":"Hasty","ivs":{"hp":8,"attack":18,"defense":23,"special_attack":18,"special_defense":13,"speed":21},"evs":{"hp":0,"attack":0,"defense":0,"special_attack":0,"special_defense":0,"speed":0},"moves":[232,372,163,400],"exp":175616,"id":625,"pass":"nFEVlnvp","cpass":"zHcAcMQV","symbol":"","ability":"defiant"}],"inv":{"1":"OOO","2":"Speed","3":"Sp Attack","4":"Attack","5":"Sp Defence","6":"Defence","pc":1925,"region":"kalos-mountain","exp":0,"avtar":"1","template":"1","id":"grey","data":"black","hometown":"Alola","name":"DexFlex","team":"1"},"balls":{"regular":48,"great":0,"ultra":9,"safari":0},"extra":{"date":"25/02/2024","megas":{},"huntd":"2024-02-27","hunts":804,"saf":"kalos","lastsafari":"2024-02-27","referred":662666053,"display":"iv-points","sort":"name","rankRewards":{"claimedLevel":0,"lastClaimAtUtc":null},"rankLevel":1},"pokecaught":["litten","crawdaunt","mewtwo","dragonite","magnemite","electabuzz","sneasel-hisui","basculegion-female","riolu","dialga","onix","magneton","scyther","greninja-ash","yveltal","bisharp","delphox","kakuna","weepinbell","trapinch","skorupi","pikachu-hoenn-cap","pikachu-sinnoh-cap","pikachu-cosplay","pikachu-sinnoh-cap","pikachu-sinnoh-cap","pikachu-belle","ditto","karrablast","swinub","sliggoo","gabite","absol","morgrem","girafarig","sandy-shocks"],"pokeseen":["litten","pidgey","kangaskhan","dratini","crawdaunt","geodude","weepinbell","rhydon","charmeleon","mewtwo","dragonite","lapras","farfetchd","magnemite","machoke","electabuzz","kakuna","aerodactyl","bulbasaur","mr-mime","spearow","dragonair","rhyhorn","oddish","lickitung","machop","graveler","seel","drowzee","bellsprout","seadra","nidorina","tentacool","staryu","tauros","metapod","scyther","charmander","krabby","exeggcute","magmar","koffing","squirtle","sandshrew","venonat","nidoran-m","ekans","porygon","zubat","grimer","rattata","tangela","weedle","clefairy","doduo","abra","golbat","nidoran-f","kabuto","mankey","poliwag","horsea","pidgeotto","haunter","poliwhirl","jigglypuff","diglett","ponyta","caterpie","pinsir","pikachu-partner-cap","wartortle","chansey","magikarp","magneton","voltorb","gastly","cubone","kadabra","paras","goldeen","nidorino","omanyte","meowth","eevee","primeape","psyduck","gloom","pikachu-cosplay","shellder","vulpix","pikachu-sinnoh-cap","slowpoke","growlithe","ivysaur","onix","budew","yanma","shieldon","munchlax","buneary","porygon2","chimchar","barboach","wormadam-sandy","spheal","dusclops","croagunk","chatot","quilava","remoraid","silcoon","finneon","luxio","petilil","cascoon","monferno","rowlet","cyndaquil","turtwig","ralts","bidoof","swinub","cleffa","stantler","sneasel-hisui","growlithe-hisui","pachirisu","prinplup","combee","wurmple","zorua-hisui","gabite","kricketot","kirlia","glameow","nosepass","murkrow","unown-i","grotle","mime-jr","aipom","bronzor","stunky","snover","starly","pichu","eevee-starter","pikachu","sliggoo-hisui","hippopotas","misdreavus","cherubi","happiny","togepi","basculegion-female","cranidos","sealeo","shinx","piplup","drifloon","staravia","gligar","voltorb-hisui","riolu","mantyke","goomy","basculin-red-striped","buizel","dartrix","unown-p","basculegion-male","dreepy","gurdurr","timburr","aron","carbink","vanillish","lairon","elekid","joltik","karrablast","deino","indeedee-male","sizzlipede","noibat","hattrem","litwick","solosis","sableye","golett","archen","pincurchin","pupitar","smoochum","amaura","tirtouga","beldum","linoone-galar","metang","sneasel","morgrem","regigigas","dialga","arceus-poison","bergmite","gible","skorupi","rufflet","dewott","bonsly","basculin-white-striped","teddiursa","snorunt","qwilfish-hisui","unown-n","unown-w","piloswine","wyrdeer","basculin-blue-striped","roselia","carnivine","chingling","oshawott","duskull","togetic","naclstack","yveltal","greninja-battle-bond","volcanion","greninja-ash","bisharp","klefki","zygarde-50-power-construct","delphox","talonflame","blacephalon","trapinch","pikachu-hoenn-cap","pikachu-belle","ditto","sliggoo","absol","cyclizar","girafarig","sandy-shocks","carkol","tauros-paldea-combat-breed","lotad","cubchoo","gourgeist-super","heatmor","torkoal","lombre","druddigon","gothita","purrloin","ursaring","pawniard","shuppet","gothorita","vibrava","wooper","larvitar","poochyena","slugma","lampent","durant","zorua","spinarak","phantump","hoothoot","pumpkaboo-super","zweilous","igglybuff","pumpkaboo-small","vanillite","spinda","trubbish","swablu","gourgeist-small","foongus","shelmet","patrat"],"teams":{"1":["JjvunLNd","3Z6liL2x","Ku4VcUtO","X8oAXbGw"],"2":["s794H4qE","TW4cjnTS","rDnM4HBb","p2A3zDH4","MoDhqctm","2wY55pnD"],"3":["QPu0MVZ6","FfSjWeAG","5yFIYhUd","rOtLEYPP","28ExElzR","ywPYqCgM"],"4":["TDWaZUCL","JjvunLNd","gegyIqcT"],"5":[],"6":["2rESs2GM"]},"tms":{"58":1}},"reset":false}]